[
 {
  "seqid": "1",
  "seqnum": 0,
  "seqtot": 81,
  "expType": "object",
  "propid": "2023B-184194",
  "object": "IBIS_wide_M490_403847",
  "expTime":       500.000,
  "efftime":       300.000,
  "filter": "M490",
  "approx_datetime": "2024/12/01 00:47:16.00",
  "approx_airmass":       1.03795,
  "RA": 10.253,
  "dec": -14.658
 },
 {
  "seqid": "1",
  "seqnum": 1,
  "seqtot": 81,
  "expType": "object",
  "propid": "2023B-184194",
  "object": "IBIS_wide_M490_400840",
  "expTime":       500.000,
  "efftime":       300.000,
  "filter": "M490",
  "approx_datetime": "2024/12/01 00:52:51.00",
  "approx_airmass":       1.03836,
  "RA": 11.488,
  "dec": -14.589
 },
 {
  "seqid": "1",
  "seqnum": 2,
  "seqtot": 81,
  "expType": "object",
  "propid": "2023B-184194",
  "object": "IBIS_wide_M490_400850",
  "expTime":       500.000,
  "efftime":       300.000,
  "filter": "M490",
  "approx_datetime": "2024/12/01 00:58:26.00",
  "approx_airmass":       1.03880,
  "RA": 13.436,
  "dec": -14.472
 },
 {
  "seqid": "1",
  "seqnum": 3,
  "seqtot": 81,
  "expType": "object",
  "propid": "2023B-184194",
  "object": "IBIS_wide_M490_403830",
  "expTime":       500.000,
  "efftime":       300.000,
  "filter": "M490",
  "approx_datetime": "2024/12/01 01:04:01.00",
  "approx_airmass":       1.03682,
  "RA": 14.466,
  "dec": -14.885
 },
 {
  "seqid": "1",
  "seqnum": 4,
  "seqtot": 81,
  "expType": "object",
  "propid": "2023B-184194",
  "object": "IBIS_wide_M490_403835",
  "expTime":       500.000,
  "efftime":       300.000,
  "filter": "M490",
  "approx_datetime": "2024/12/01 01:09:36.00",
  "approx_airmass":       1.03964,
  "RA": 12.905,
  "dec": -14.741
 },
 {
  "seqid": "1",
  "seqnum": 5,
  "seqtot": 81,
  "expType": "object",
  "propid": "2023B-184194",
  "object": "IBIS_wide_M490_403831",
  "expTime":       500.000,
  "efftime":       300.000,
  "filter": "M490",
  "approx_datetime": "2024/12/01 01:15:11.00",
  "approx_airmass":       1.03792,
  "RA": 15.789,
  "dec": -14.814
 },
 {
  "seqid": "1",
  "seqnum": 6,
  "seqtot": 81,
  "expType": "object",
  "propid": "2023B-184194",
  "object": "IBIS_wide_M490_400846",
  "expTime":       500.000,
  "efftime":       300.000,
  "filter": "M490",
  "approx_datetime": "2024/12/01 01:20:46.00",
  "approx_airmass":       1.04024,
  "RA": 16.094,
  "dec": -14.540
 },
 {
  "seqid": "1",
  "seqnum": 7,
  "seqtot": 81,
  "expType": "object",
  "propid": "2023B-184194",
  "object": "IBIS_wide_M490_403832",
  "expTime":       500.000,
  "efftime":       300.000,
  "filter": "M490",
  "approx_datetime": "2024/12/01 01:26:21.00",
  "approx_airmass":       1.04283,
  "RA": 16.556,
  "dec": -14.247
 },
 {
  "seqid": "1",
  "seqnum": 8,
  "seqtot": 81,
  "expType": "object",
  "propid": "2023B-184194",
  "object": "IBIS_wide_M490_401067",
  "expTime":       500.000,
  "efftime":       300.000,
  "filter": "M490",
  "approx_datetime": "2024/12/01 01:31:56.00",
  "approx_airmass":       1.04224,
  "RA": 17.548,
  "dec": -14.466
 },
 {
  "seqid": "1",
  "seqnum": 9,
  "seqtot": 81,
  "expType": "object",
  "propid": "2023B-184194",
  "object": "IBIS_wide_M490_401060",
  "expTime":       500.000,
  "efftime":       300.000,
  "filter": "M490",
  "approx_datetime": "2024/12/01 01:37:31.00",
  "approx_airmass":       1.03984,
  "RA": 19.540,
  "dec": -14.786
 },
 {
  "seqid": "1",
  "seqnum": 10,
  "seqtot": 81,
  "expType": "object",
  "propid": "2023B-184194",
  "object": "IBIS_wide_M490_404051",
  "expTime":       500.000,
  "efftime":       300.000,
  "filter": "M490",
  "approx_datetime": "2024/12/01 01:43:06.00",
  "approx_airmass":       1.04256,
  "RA": 18.548,
  "dec": -14.984
 },
 {
  "seqid": "1",
  "seqnum": 11,
  "seqtot": 81,
  "expType": "object",
  "propid": "2023B-184194",
  "object": "IBIS_wide_M490_401066",
  "expTime":       500.000,
  "efftime":       300.000,
  "filter": "M490",
  "approx_datetime": "2024/12/01 01:48:41.00",
  "approx_airmass":       1.04629,
  "RA": 18.973,
  "dec": -14.638
 },
 {
  "seqid": "1",
  "seqnum": 12,
  "seqtot": 81,
  "expType": "object",
  "propid": "2023B-184194",
  "object": "IBIS_wide_M490_401061",
  "expTime":       500.000,
  "efftime":       300.000,
  "filter": "M490",
  "approx_datetime": "2024/12/01 01:54:16.00",
  "approx_airmass":       1.04336,
  "RA": 20.967,
  "dec": -14.970
 },
 {
  "seqid": "1",
  "seqnum": 13,
  "seqtot": 81,
  "expType": "object",
  "propid": "2023B-184194",
  "object": "IBIS_wide_M490_404047",
  "expTime":       500.000,
  "efftime":       300.000,
  "filter": "M490",
  "approx_datetime": "2024/12/01 01:59:51.00",
  "approx_airmass":       1.04559,
  "RA": 21.631,
  "dec": -14.835
 },
 {
  "seqid": "1",
  "seqnum": 14,
  "seqtot": 81,
  "expType": "object",
  "propid": "2023B-184194",
  "object": "IBIS_wide_M490_404037",
  "expTime":       500.000,
  "efftime":       300.000,
  "filter": "M490",
  "approx_datetime": "2024/12/01 02:05:26.00",
  "approx_airmass":       1.04834,
  "RA": 23.570,
  "dec": -14.086
 },
 {
  "seqid": "1",
  "seqnum": 15,
  "seqtot": 81,
  "expType": "object",
  "propid": "2023B-184194",
  "object": "IBIS_wide_M490_404026",
  "expTime":       500.000,
  "efftime":       300.000,
  "filter": "M490",
  "approx_datetime": "2024/12/01 02:11:01.00",
  "approx_airmass":       1.04943,
  "RA": 22.886,
  "dec": -14.817
 },
 {
  "seqid": "1",
  "seqnum": 16,
  "seqtot": 81,
  "expType": "object",
  "propid": "2023B-184194",
  "object": "IBIS_wide_M490_401051",
  "expTime":       500.000,
  "efftime":       300.000,
  "filter": "M490",
  "approx_datetime": "2024/12/01 02:16:36.00",
  "approx_airmass":       1.05352,
  "RA": 23.315,
  "dec": -14.552
 },
 {
  "seqid": "1",
  "seqnum": 17,
  "seqtot": 81,
  "expType": "object",
  "propid": "2023B-184194",
  "object": "IBIS_wide_M490_401050",
  "expTime":       500.000,
  "efftime":       300.000,
  "filter": "M490",
  "approx_datetime": "2024/12/01 02:22:11.00",
  "approx_airmass":       1.05420,
  "RA": 24.619,
  "dec": -14.478
 },
 {
  "seqid": "1",
  "seqnum": 18,
  "seqtot": 81,
  "expType": "object",
  "propid": "2023B-184194",
  "object": "IBIS_wide_M490_404036",
  "expTime":       500.000,
  "efftime":       300.000,
  "filter": "M490",
  "approx_datetime": "2024/12/01 02:27:46.00",
  "approx_airmass":       1.05879,
  "RA": 25.010,
  "dec": -14.211
 },
 {
  "seqid": "1",
  "seqnum": 19,
  "seqtot": 81,
  "expType": "object",
  "propid": "2023B-184194",
  "object": "IBIS_wide_M490_404030",
  "expTime":       500.000,
  "efftime":       300.000,
  "filter": "M490",
  "approx_datetime": "2024/12/01 02:33:21.00",
  "approx_airmass":       1.05825,
  "RA": 25.725,
  "dec": -14.741
 },
 {
  "seqid": "1",
  "seqnum": 20,
  "seqtot": 81,
  "expType": "object",
  "propid": "2023B-184194",
  "object": "IBIS_wide_M490_404031",
  "expTime":       500.000,
  "efftime":       300.000,
  "filter": "M490",
  "approx_datetime": "2024/12/01 02:38:56.00",
  "approx_airmass":       1.05851,
  "RA": 26.954,
  "dec": -14.804
 },
 {
  "seqid": "1",
  "seqnum": 21,
  "seqtot": 81,
  "expType": "object",
  "propid": "2023B-184194",
  "object": "IBIS_wide_M490_401089",
  "expTime":       500.000,
  "efftime":       300.000,
  "filter": "M490",
  "approx_datetime": "2024/12/01 02:44:31.00",
  "approx_airmass":       1.06513,
  "RA": 28.122,
  "dec": -13.750
 },
 {
  "seqid": "1",
  "seqnum": 22,
  "seqtot": 81,
  "expType": "object",
  "propid": "2023B-184194",
  "object": "IBIS_wide_M490_405939",
  "expTime":       500.000,
  "efftime":       300.000,
  "filter": "M490",
  "approx_datetime": "2024/12/01 02:50:06.00",
  "approx_airmass":       1.06332,
  "RA": 28.510,
  "dec": -14.767
 },
 {
  "seqid": "1",
  "seqnum": 23,
  "seqtot": 81,
  "expType": "object",
  "propid": "2023B-184194",
  "object": "IBIS_wide_M490_405968",
  "expTime":       500.000,
  "efftime":       300.000,
  "filter": "M490",
  "approx_datetime": "2024/12/01 02:55:41.00",
  "approx_airmass":       1.07118,
  "RA": 28.789,
  "dec": -14.171
 },
 {
  "seqid": "1",
  "seqnum": 24,
  "seqtot": 81,
  "expType": "object",
  "propid": "2023B-184194",
  "object": "IBIS_wide_M490_402974",
  "expTime":       500.000,
  "efftime":       300.000,
  "filter": "M490",
  "approx_datetime": "2024/12/01 03:01:16.00",
  "approx_airmass":       1.07809,
  "RA": 31.688,
  "dec": -12.005
 },
 {
  "seqid": "1",
  "seqnum": 25,
  "seqtot": 81,
  "expType": "object",
  "propid": "2023B-184194",
  "object": "IBIS_wide_M490_402958",
  "expTime":       500.000,
  "efftime":       300.000,
  "filter": "M490",
  "approx_datetime": "2024/12/01 03:06:51.00",
  "approx_airmass":       1.07566,
  "RA": 30.198,
  "dec": -14.485
 },
 {
  "seqid": "1",
  "seqnum": 26,
  "seqtot": 81,
  "expType": "object",
  "propid": "2023B-184194",
  "object": "IBIS_wide_M490_402962",
  "expTime":       500.000,
  "efftime":       300.000,
  "filter": "M490",
  "approx_datetime": "2024/12/01 03:12:26.00",
  "approx_airmass":       1.08268,
  "RA": 31.675,
  "dec": -13.228
 },
 {
  "seqid": "1",
  "seqnum": 27,
  "seqtot": 81,
  "expType": "object",
  "propid": "2023B-184194",
  "object": "IBIS_wide_M490_402961",
  "expTime":       500.000,
  "efftime":       300.000,
  "filter": "M490",
  "approx_datetime": "2024/12/01 03:18:01.00",
  "approx_airmass":       1.09018,
  "RA": 30.914,
  "dec": -13.810
 },
 {
  "seqid": "1",
  "seqnum": 28,
  "seqtot": 81,
  "expType": "object",
  "propid": "2023B-184194",
  "object": "IBIS_wide_M490_405981",
  "expTime":       500.000,
  "efftime":       300.000,
  "filter": "M490",
  "approx_datetime": "2024/12/01 03:23:36.00",
  "approx_airmass":       1.09720,
  "RA": 32.672,
  "dec": -12.392
 },
 {
  "seqid": "1",
  "seqnum": 29,
  "seqtot": 81,
  "expType": "object",
  "propid": "2023B-184194",
  "object": "IBIS_wide_M490_402956",
  "expTime":       500.000,
  "efftime":       300.000,
  "filter": "M490",
  "approx_datetime": "2024/12/01 03:29:11.00",
  "approx_airmass":       1.09606,
  "RA": 32.854,
  "dec": -13.637
 },
 {
  "seqid": "1",
  "seqnum": 30,
  "seqtot": 81,
  "expType": "object",
  "propid": "2023B-184194",
  "object": "IBIS_wide_M490_402965",
  "expTime":       500.000,
  "efftime":       300.000,
  "filter": "M490",
  "approx_datetime": "2024/12/01 03:34:46.00",
  "approx_airmass":       1.09774,
  "RA": 33.729,
  "dec": -13.862
 },
 {
  "seqid": "1",
  "seqnum": 31,
  "seqtot": 81,
  "expType": "object",
  "propid": "2023B-184194",
  "object": "IBIS_wide_M490_402948",
  "expTime":       500.000,
  "efftime":       300.000,
  "filter": "M490",
  "approx_datetime": "2024/12/01 03:40:21.00",
  "approx_airmass":       1.09873,
  "RA": 35.124,
  "dec": -13.707
 },
 {
  "seqid": "1",
  "seqnum": 32,
  "seqtot": 81,
  "expType": "object",
  "propid": "2023B-184194",
  "object": "IBIS_wide_M490_405957",
  "expTime":       500.000,
  "efftime":       300.000,
  "filter": "M490",
  "approx_datetime": "2024/12/01 03:45:56.00",
  "approx_airmass":       1.10305,
  "RA": 35.832,
  "dec": -13.688
 },
 {
  "seqid": "1",
  "seqnum": 33,
  "seqtot": 81,
  "expType": "object",
  "propid": "2023B-184194",
  "object": "IBIS_wide_M490_400915",
  "expTime":       500.000,
  "efftime":       300.000,
  "filter": "M490",
  "approx_datetime": "2024/12/01 03:51:31.00",
  "approx_airmass":       1.11027,
  "RA": 35.891,
  "dec": -13.910
 },
 {
  "seqid": "1",
  "seqnum": 34,
  "seqtot": 81,
  "expType": "object",
  "propid": "2023B-184194",
  "object": "IBIS_wide_M490_405955",
  "expTime":       500.000,
  "efftime":       300.000,
  "filter": "M490",
  "approx_datetime": "2024/12/01 03:57:06.00",
  "approx_airmass":       1.12000,
  "RA": 35.416,
  "dec": -14.444
 },
 {
  "seqid": "1",
  "seqnum": 35,
  "seqtot": 81,
  "expType": "object",
  "propid": "2023B-184194",
  "object": "IBIS_wide_M490_409887",
  "expTime":       500.000,
  "efftime":       300.000,
  "filter": "M490",
  "approx_datetime": "2024/12/01 04:02:41.00",
  "approx_airmass":       1.11816,
  "RA": 37.388,
  "dec": -14.083
 },
 {
  "seqid": "1",
  "seqnum": 36,
  "seqtot": 81,
  "expType": "object",
  "propid": "2023B-184194",
  "object": "IBIS_wide_M490_409892",
  "expTime":       500.000,
  "efftime":       300.000,
  "filter": "M490",
  "approx_datetime": "2024/12/01 04:08:16.00",
  "approx_airmass":       1.12678,
  "RA": 39.184,
  "dec": -12.384
 },
 {
  "seqid": "1",
  "seqnum": 37,
  "seqtot": 81,
  "expType": "object",
  "propid": "2023B-184194",
  "object": "IBIS_wide_M490_409883",
  "expTime":       500.000,
  "efftime":       300.000,
  "filter": "M490",
  "approx_datetime": "2024/12/01 04:13:51.00",
  "approx_airmass":       1.12327,
  "RA": 39.688,
  "dec": -13.854
 },
 {
  "seqid": "1",
  "seqnum": 38,
  "seqtot": 81,
  "expType": "object",
  "propid": "2023B-184194",
  "object": "IBIS_wide_M490_406898",
  "expTime":       500.000,
  "efftime":       300.000,
  "filter": "M490",
  "approx_datetime": "2024/12/01 04:19:26.00",
  "approx_airmass":       1.12974,
  "RA": 40.148,
  "dec": -13.948
 },
 {
  "seqid": "1",
  "seqnum": 39,
  "seqtot": 81,
  "expType": "object",
  "propid": "2023B-184194",
  "object": "IBIS_wide_M490_409909",
  "expTime":       500.000,
  "efftime":       300.000,
  "filter": "M490",
  "approx_datetime": "2024/12/01 04:25:01.00",
  "approx_airmass":       1.13572,
  "RA": 42.958,
  "dec": -11.583
 },
 {
  "seqid": "1",
  "seqnum": 40,
  "seqtot": 81,
  "expType": "object",
  "propid": "2023B-184194",
  "object": "IBIS_wide_M490_409802",
  "expTime":       500.000,
  "efftime":       300.000,
  "filter": "M490",
  "approx_datetime": "2024/12/01 04:30:36.00",
  "approx_airmass":       1.13187,
  "RA": 41.961,
  "dec": -14.813
 },
 {
  "seqid": "1",
  "seqnum": 41,
  "seqtot": 81,
  "expType": "object",
  "propid": "2023B-184194",
  "object": "IBIS_wide_M490_409846",
  "expTime":       500.000,
  "efftime":       300.000,
  "filter": "M490",
  "approx_datetime": "2024/12/01 04:36:11.00",
  "approx_airmass":       1.14052,
  "RA": 43.240,
  "dec": -13.659
 },
 {
  "seqid": "1",
  "seqnum": 42,
  "seqtot": 81,
  "expType": "object",
  "propid": "2023B-184194",
  "object": "IBIS_wide_M490_406858",
  "expTime":       500.000,
  "efftime":       300.000,
  "filter": "M490",
  "approx_datetime": "2024/12/01 04:41:46.00",
  "approx_airmass":       1.14182,
  "RA": 43.671,
  "dec": -14.665
 },
 {
  "seqid": "1",
  "seqnum": 43,
  "seqtot": 81,
  "expType": "object",
  "propid": "2023B-184194",
  "object": "IBIS_wide_M490_409838",
  "expTime":       500.000,
  "efftime":       300.000,
  "filter": "M490",
  "approx_datetime": "2024/12/01 04:47:21.00",
  "approx_airmass":       1.14383,
  "RA": 44.840,
  "dec": -14.659
 },
 {
  "seqid": "1",
  "seqnum": 44,
  "seqtot": 81,
  "expType": "object",
  "propid": "2023B-184194",
  "object": "IBIS_wide_M490_406832",
  "expTime":       500.000,
  "efftime":       300.000,
  "filter": "M490",
  "approx_datetime": "2024/12/01 04:52:56.00",
  "approx_airmass":       1.13389,
  "RA": 47.488,
  "dec": -14.589
 },
 {
  "seqid": "1",
  "seqnum": 45,
  "seqtot": 81,
  "expType": "object",
  "propid": "2023B-184194",
  "object": "IBIS_wide_M490_406842",
  "expTime":       500.000,
  "efftime":       300.000,
  "filter": "M490",
  "approx_datetime": "2024/12/01 04:58:31.00",
  "approx_airmass":       1.13028,
  "RA": 49.436,
  "dec": -14.472
 },
 {
  "seqid": "1",
  "seqnum": 46,
  "seqtot": 81,
  "expType": "object",
  "propid": "2023B-184194",
  "object": "IBIS_wide_M490_409825",
  "expTime":       500.000,
  "efftime":       300.000,
  "filter": "M490",
  "approx_datetime": "2024/12/01 05:04:06.00",
  "approx_airmass":       1.12841,
  "RA": 51.087,
  "dec": -14.456
 },
 {
  "seqid": "1",
  "seqnum": 47,
  "seqtot": 81,
  "expType": "object",
  "propid": "2023B-184194",
  "object": "IBIS_wide_M490_407145",
  "expTime":       500.000,
  "efftime":       300.000,
  "filter": "M490",
  "approx_datetime": "2024/12/01 05:09:41.00",
  "approx_airmass":       1.12960,
  "RA": 52.861,
  "dec": -13.835
 },
 {
  "seqid": "1",
  "seqnum": 48,
  "seqtot": 81,
  "expType": "object",
  "propid": "2023B-184194",
  "object": "IBIS_wide_M490_410038",
  "expTime":       500.000,
  "efftime":       300.000,
  "filter": "M490",
  "approx_datetime": "2024/12/01 05:15:16.00",
  "approx_airmass":       1.11025,
  "RA": 56.041,
  "dec": -14.838
 },
 {
  "seqid": "1",
  "seqnum": 49,
  "seqtot": 81,
  "expType": "object",
  "propid": "2023B-184194",
  "object": "IBIS_wide_M490_410047",
  "expTime":       500.000,
  "efftime":       300.000,
  "filter": "M490",
  "approx_datetime": "2024/12/01 05:20:51.00",
  "approx_airmass":       1.12887,
  "RA": 55.996,
  "dec": -13.560
 },
 {
  "seqid": "1",
  "seqnum": 50,
  "seqtot": 81,
  "expType": "object",
  "propid": "2023B-184194",
  "object": "IBIS_wide_M490_407059",
  "expTime":       500.000,
  "efftime":       300.000,
  "filter": "M490",
  "approx_datetime": "2024/12/01 05:26:26.00",
  "approx_airmass":       1.15476,
  "RA": 53.548,
  "dec": -14.466
 },
 {
  "seqid": "1",
  "seqnum": 51,
  "seqtot": 81,
  "expType": "object",
  "propid": "2023B-184194",
  "object": "IBIS_wide_M490_409738",
  "expTime":       500.000,
  "efftime":       300.000,
  "filter": "M490",
  "approx_datetime": "2024/12/01 05:32:01.00",
  "approx_airmass":       1.16856,
  "RA": 53.152,
  "dec": -14.927
 },
 {
  "seqid": "1",
  "seqnum": 52,
  "seqtot": 81,
  "expType": "object",
  "propid": "2023B-184194",
  "object": "IBIS_wide_M490_407146",
  "expTime":       500.000,
  "efftime":       300.000,
  "filter": "M490",
  "approx_datetime": "2024/12/01 05:37:36.00",
  "approx_airmass":       1.18339,
  "RA": 54.089,
  "dec": -13.535
 },
 {
  "seqid": "1",
  "seqnum": 53,
  "seqtot": 81,
  "expType": "object",
  "propid": "2023B-184194",
  "object": "IBIS_wide_M490_410136",
  "expTime":       500.000,
  "efftime":       300.000,
  "filter": "M490",
  "approx_datetime": "2024/12/01 05:43:11.00",
  "approx_airmass":       1.19827,
  "RA": 55.330,
  "dec": -11.895
 },
 {
  "seqid": "1",
  "seqnum": 54,
  "seqtot": 81,
  "expType": "object",
  "propid": "2023B-184194",
  "object": "IBIS_wide_M490_410135",
  "expTime":       500.000,
  "efftime":       300.000,
  "filter": "M490",
  "approx_datetime": "2024/12/01 05:48:46.00",
  "approx_airmass":       1.21775,
  "RA": 54.443,
  "dec": -12.615
 },
 {
  "seqid": "1",
  "seqnum": 55,
  "seqtot": 81,
  "expType": "object",
  "propid": "2023B-184194",
  "object": "IBIS_wide_M490_407150",
  "expTime":       500.000,
  "efftime":       300.000,
  "filter": "M490",
  "approx_datetime": "2024/12/01 05:54:21.00",
  "approx_airmass":       1.23490,
  "RA": 54.868,
  "dec": -12.006
 },
 {
  "seqid": "1",
  "seqnum": 56,
  "seqtot": 81,
  "expType": "object",
  "propid": "2023B-184194",
  "object": "IBIS_wide_M490_410132",
  "expTime":       500.000,
  "efftime":       300.000,
  "filter": "M490",
  "approx_datetime": "2024/12/01 05:59:56.00",
  "approx_airmass":       1.25487,
  "RA": 54.054,
  "dec": -12.963
 },
 {
  "seqid": "1",
  "seqnum": 57,
  "seqtot": 81,
  "expType": "object",
  "propid": "2023B-184194",
  "object": "IBIS_wide_M490_407163",
  "expTime":       500.000,
  "efftime":       300.000,
  "filter": "M490",
  "approx_datetime": "2024/12/01 06:05:31.00",
  "approx_airmass":       1.27503,
  "RA": 54.975,
  "dec": -11.548
 },
 {
  "seqid": "1",
  "seqnum": 58,
  "seqtot": 81,
  "expType": "object",
  "propid": "2023B-184194",
  "object": "IBIS_wide_M490_410131",
  "expTime":       500.000,
  "efftime":       300.000,
  "filter": "M490",
  "approx_datetime": "2024/12/01 06:11:06.00",
  "approx_airmass":       1.30132,
  "RA": 53.279,
  "dec": -13.568
 },
 {
  "seqid": "1",
  "seqnum": 59,
  "seqtot": 81,
  "expType": "object",
  "propid": "2023B-184194",
  "object": "IBIS_wide_M490_410138",
  "expTime":       500.000,
  "efftime":       300.000,
  "filter": "M490",
  "approx_datetime": "2024/12/01 06:16:41.00",
  "approx_airmass":       1.32795,
  "RA": 54.614,
  "dec": -11.129
 },
 {
  "seqid": "1",
  "seqnum": 60,
  "seqtot": 81,
  "expType": "object",
  "propid": "2023B-184194",
  "object": "IBIS_wide_M490_419241",
  "expTime":       500.000,
  "efftime":       300.000,
  "filter": "M490",
  "approx_datetime": "2024/12/01 06:22:16.00",
  "approx_airmass":       1.34799,
  "RA": 130.491,
  "dec": -4.184
 },
 {
  "seqid": "1",
  "seqnum": 61,
  "seqtot": 81,
  "expType": "object",
  "propid": "2023B-184194",
  "object": "IBIS_wide_M490_419219",
  "expTime":       500.000,
  "efftime":       300.000,
  "filter": "M490",
  "approx_datetime": "2024/12/01 06:27:51.00",
  "approx_airmass":       1.32916,
  "RA": 131.208,
  "dec": -4.782
 },
 {
  "seqid": "1",
  "seqnum": 62,
  "seqtot": 81,
  "expType": "object",
  "propid": "2023B-184194",
  "object": "IBIS_wide_M490_419217",
  "expTime":       500.000,
  "efftime":       300.000,
  "filter": "M490",
  "approx_datetime": "2024/12/01 06:33:26.00",
  "approx_airmass":       1.30983,
  "RA": 131.937,
  "dec": -5.498
 },
 {
  "seqid": "1",
  "seqnum": 63,
  "seqtot": 81,
  "expType": "object",
  "propid": "2023B-184194",
  "object": "IBIS_wide_M490_422235",
  "expTime":       500.000,
  "efftime":       300.000,
  "filter": "M490",
  "approx_datetime": "2024/12/01 06:39:01.00",
  "approx_airmass":       1.29471,
  "RA": 129.459,
  "dec": -2.706
 },
 {
  "seqid": "1",
  "seqnum": 64,
  "seqtot": 81,
  "expType": "object",
  "propid": "2023B-184194",
  "object": "IBIS_wide_M490_419211",
  "expTime":       500.000,
  "efftime":       300.000,
  "filter": "M490",
  "approx_datetime": "2024/12/01 06:44:36.00",
  "approx_airmass":       1.27729,
  "RA": 132.824,
  "dec": -6.019
 },
 {
  "seqid": "1",
  "seqnum": 65,
  "seqtot": 81,
  "expType": "object",
  "propid": "2023B-184194",
  "object": "IBIS_wide_M490_419220",
  "expTime":       500.000,
  "efftime":       300.000,
  "filter": "M490",
  "approx_datetime": "2024/12/01 06:50:11.00",
  "approx_airmass":       1.26963,
  "RA": 131.922,
  "dec": -4.309
 },
 {
  "seqid": "1",
  "seqnum": 66,
  "seqtot": 81,
  "expType": "object",
  "propid": "2023B-184194",
  "object": "IBIS_wide_M490_419210",
  "expTime":       500.000,
  "efftime":       300.000,
  "filter": "M490",
  "approx_datetime": "2024/12/01 06:55:46.00",
  "approx_airmass":       1.25774,
  "RA": 134.007,
  "dec": -5.973
 },
 {
  "seqid": "1",
  "seqnum": 67,
  "seqtot": 81,
  "expType": "object",
  "propid": "2023B-184194",
  "object": "IBIS_wide_M490_422198",
  "expTime":       500.000,
  "efftime":       300.000,
  "filter": "M490",
  "approx_datetime": "2024/12/01 07:01:21.00",
  "approx_airmass":       1.24778,
  "RA": 133.647,
  "dec": -5.086
 },
 {
  "seqid": "1",
  "seqnum": 68,
  "seqtot": 81,
  "expType": "object",
  "propid": "2023B-184194",
  "object": "IBIS_wide_M490_419213",
  "expTime":       500.000,
  "efftime":       300.000,
  "filter": "M490",
  "approx_datetime": "2024/12/01 07:06:56.00",
  "approx_airmass":       1.24190,
  "RA": 134.803,
  "dec": -5.359
 },
 {
  "seqid": "1",
  "seqnum": 69,
  "seqtot": 81,
  "expType": "object",
  "propid": "2023B-184194",
  "object": "IBIS_wide_M490_419125",
  "expTime":       500.000,
  "efftime":       300.000,
  "filter": "M490",
  "approx_datetime": "2024/12/01 07:12:31.00",
  "approx_airmass":       1.22819,
  "RA": 136.125,
  "dec": -6.507
 },
 {
  "seqid": "1",
  "seqnum": 70,
  "seqtot": 81,
  "expType": "object",
  "propid": "2023B-184194",
  "object": "IBIS_wide_M490_422111",
  "expTime":       500.000,
  "efftime":       300.000,
  "filter": "M490",
  "approx_datetime": "2024/12/01 07:18:06.00",
  "approx_airmass":       1.21844,
  "RA": 136.373,
  "dec": -6.302
 },
 {
  "seqid": "1",
  "seqnum": 71,
  "seqtot": 81,
  "expType": "object",
  "propid": "2023B-184194",
  "object": "IBIS_wide_M490_419126",
  "expTime":       500.000,
  "efftime":       300.000,
  "filter": "M490",
  "approx_datetime": "2024/12/01 07:23:41.00",
  "approx_airmass":       1.21182,
  "RA": 136.825,
  "dec": -6.045
 },
 {
  "seqid": "1",
  "seqnum": 72,
  "seqtot": 81,
  "expType": "object",
  "propid": "2023B-184194",
  "object": "IBIS_wide_M490_422106",
  "expTime":       500.000,
  "efftime":       300.000,
  "filter": "M490",
  "approx_datetime": "2024/12/01 07:29:16.00",
  "approx_airmass":       1.20605,
  "RA": 137.893,
  "dec": -6.289
 },
 {
  "seqid": "1",
  "seqnum": 73,
  "seqtot": 81,
  "expType": "object",
  "propid": "2023B-184194",
  "object": "IBIS_wide_M490_419277",
  "expTime":       500.000,
  "efftime":       300.000,
  "filter": "M490",
  "approx_datetime": "2024/12/01 07:34:51.00",
  "approx_airmass":       1.19940,
  "RA": 138.318,
  "dec": -6.063
 },
 {
  "seqid": "1",
  "seqnum": 74,
  "seqtot": 81,
  "expType": "object",
  "propid": "2023B-184194",
  "object": "IBIS_wide_M490_422252",
  "expTime":       500.000,
  "efftime":       300.000,
  "filter": "M490",
  "approx_datetime": "2024/12/01 07:40:26.00",
  "approx_airmass":       1.19468,
  "RA": 140.129,
  "dec": -6.885
 },
 {
  "seqid": "1",
  "seqnum": 75,
  "seqtot": 81,
  "expType": "object",
  "propid": "2023B-184194",
  "object": "IBIS_wide_M490_419276",
  "expTime":       500.000,
  "efftime":       300.000,
  "filter": "M490",
  "approx_datetime": "2024/12/01 07:46:01.00",
  "approx_airmass":       1.18649,
  "RA": 139.526,
  "dec": -5.976
 },
 {
  "seqid": "1",
  "seqnum": 76,
  "seqtot": 81,
  "expType": "object",
  "propid": "2023B-184194",
  "object": "IBIS_wide_M490_419267",
  "expTime":       500.000,
  "efftime":       300.000,
  "filter": "M490",
  "approx_datetime": "2024/12/01 07:51:36.00",
  "approx_airmass":       1.17625,
  "RA": 140.410,
  "dec": -6.577
 },
 {
  "seqid": "1",
  "seqnum": 77,
  "seqtot": 81,
  "expType": "object",
  "propid": "2023B-184194",
  "object": "IBIS_wide_M490_419268",
  "expTime":       500.000,
  "efftime":       300.000,
  "filter": "M490",
  "approx_datetime": "2024/12/01 07:57:11.00",
  "approx_airmass":       1.17407,
  "RA": 141.558,
  "dec": -6.596
 },
 {
  "seqid": "1",
  "seqnum": 78,
  "seqtot": 81,
  "expType": "object",
  "propid": "2023B-184194",
  "object": "IBIS_wide_M490_422248",
  "expTime":       500.000,
  "efftime":       300.000,
  "filter": "M490",
  "approx_datetime": "2024/12/01 08:02:46.00",
  "approx_airmass":       1.16981,
  "RA": 142.782,
  "dec": -6.893
 },
 {
  "seqid": "1",
  "seqnum": 79,
  "seqtot": 81,
  "expType": "object",
  "propid": "2023B-184194",
  "object": "IBIS_wide_M490_422254",
  "expTime":       500.000,
  "efftime":       300.000,
  "filter": "M490",
  "approx_datetime": "2024/12/01 08:08:21.00",
  "approx_airmass":       1.16068,
  "RA": 142.018,
  "dec": -6.193
 },
 {
  "seqid": "1",
  "seqnum": 80,
  "seqtot": 81,
  "expType": "object",
  "propid": "2023B-184194",
  "object": "IBIS_wide_M490_418972",
  "expTime":       500.000,
  "efftime":       300.000,
  "filter": "M490",
  "approx_datetime": "2024/12/01 08:13:56.00",
  "approx_airmass":       1.16095,
  "RA": 143.976,
  "dec": -6.573
 }
]
