[
 {
  "seqid": "1",
  "seqnum": 0,
  "seqtot": 174,
  "expType": "object",
  "propid": "2023B-184194",
  "object": "IBIS_wide_M464_351985",
  "expTime":       500.000,
  "efftime":       340.110,
  "filter": "M464",
  "approx_datetime": "2025/09/23 23:46:14.00",
  "approx_airmass":       1.09747,
  "RA": 308.752,
  "dec": -14.198
 },
 {
  "seqid": "1",
  "seqnum": 1,
  "seqtot": 174,
  "expType": "object",
  "propid": "2023B-184194",
  "object": "IBIS_wide_M464_349067",
  "expTime":       500.000,
  "efftime":       380.300,
  "filter": "M464",
  "approx_datetime": "2025/09/23 23:49:39.06",
  "approx_airmass":       1.13677,
  "RA": 310.932,
  "dec": -9.827
 },
 {
  "seqid": "1",
  "seqnum": 2,
  "seqtot": 174,
  "expType": "object",
  "propid": "2023B-184194",
  "object": "IBIS_wide_M464_352045",
  "expTime":       500.000,
  "efftime":       440.980,
  "filter": "M464",
  "approx_datetime": "2025/09/23 23:53:24.21",
  "approx_airmass":       1.13834,
  "RA": 312.889,
  "dec": -10.540
 },
 {
  "seqid": "1",
  "seqnum": 3,
  "seqtot": 174,
  "expType": "object",
  "propid": "2023B-184194",
  "object": "IBIS_wide_M464_352043",
  "expTime":       500.000,
  "efftime":       442.200,
  "filter": "M464",
  "approx_datetime": "2025/09/23 23:57:39.70",
  "approx_airmass":       1.13060,
  "RA": 313.606,
  "dec": -11.219
 },
 {
  "seqid": "1",
  "seqnum": 4,
  "seqtot": 174,
  "expType": "object",
  "propid": "2023B-184194",
  "object": "IBIS_wide_M464_352051",
  "expTime":       500.000,
  "efftime":       445.020,
  "filter": "M464",
  "approx_datetime": "2025/09/24 00:01:55.80",
  "approx_airmass":       1.12492,
  "RA": 312.315,
  "dec": -9.904
 },
 {
  "seqid": "1",
  "seqnum": 5,
  "seqtot": 174,
  "expType": "object",
  "propid": "2023B-184194",
  "object": "IBIS_wide_M464_352053",
  "expTime":       500.000,
  "efftime":       413.690,
  "filter": "M464",
  "approx_datetime": "2025/09/24 00:06:13.31",
  "approx_airmass":       1.11886,
  "RA": 311.576,
  "dec": -9.294
 },
 {
  "seqid": "1",
  "seqnum": 6,
  "seqtot": 174,
  "expType": "object",
  "propid": "2023B-184194",
  "object": "IBIS_wide_M464_352021",
  "expTime":       500.000,
  "efftime":       413.790,
  "filter": "M464",
  "approx_datetime": "2025/09/24 00:10:15.15",
  "approx_airmass":       1.11320,
  "RA": 314.471,
  "dec": -11.529
 },
 {
  "seqid": "1",
  "seqnum": 7,
  "seqtot": 174,
  "expType": "object",
  "propid": "2023B-184194",
  "object": "IBIS_wide_M464_354893",
  "expTime":       500.000,
  "efftime":       349.400,
  "filter": "M464",
  "approx_datetime": "2025/09/24 00:14:17.05",
  "approx_airmass":       1.20730,
  "RA": 325.393,
  "dec": -10.049
 },
 {
  "seqid": "1",
  "seqnum": 8,
  "seqtot": 174,
  "expType": "object",
  "propid": "2023B-184194",
  "object": "IBIS_wide_M464_357903",
  "expTime":       500.000,
  "efftime":       333.440,
  "filter": "M464",
  "approx_datetime": "2025/09/24 00:17:46.75",
  "approx_airmass":       1.20082,
  "RA": 324.652,
  "dec": -8.951
 },
 {
  "seqid": "1",
  "seqnum": 9,
  "seqtot": 174,
  "expType": "object",
  "propid": "2023B-184194",
  "object": "IBIS_wide_M464_357879",
  "expTime":       500.000,
  "efftime":       347.840,
  "filter": "M464",
  "approx_datetime": "2025/09/24 00:21:08.47",
  "approx_airmass":       1.19456,
  "RA": 325.769,
  "dec": -9.922
 },
 {
  "seqid": "1",
  "seqnum": 10,
  "seqtot": 174,
  "expType": "object",
  "propid": "2023B-184194",
  "object": "IBIS_wide_M464_354896",
  "expTime":       500.000,
  "efftime":       342.320,
  "filter": "M464",
  "approx_datetime": "2025/09/24 00:24:37.39",
  "approx_airmass":       1.19240,
  "RA": 325.477,
  "dec": -8.913
 },
 {
  "seqid": "1",
  "seqnum": 11,
  "seqtot": 174,
  "expType": "object",
  "propid": "2023B-184194",
  "object": "IBIS_wide_M464_354894",
  "expTime":       500.000,
  "efftime":       346.860,
  "filter": "M464",
  "approx_datetime": "2025/09/24 00:28:03.55",
  "approx_airmass":       1.18488,
  "RA": 326.125,
  "dec": -9.510
 },
 {
  "seqid": "1",
  "seqnum": 12,
  "seqtot": 174,
  "expType": "object",
  "propid": "2023B-184194",
  "object": "IBIS_wide_M464_357880",
  "expTime":       500.000,
  "efftime":       352.320,
  "filter": "M464",
  "approx_datetime": "2025/09/24 00:31:31.98",
  "approx_airmass":       1.18390,
  "RA": 326.512,
  "dec": -9.120
 },
 {
  "seqid": "1",
  "seqnum": 13,
  "seqtot": 174,
  "expType": "object",
  "propid": "2023B-184194",
  "object": "IBIS_wide_M464_354899",
  "expTime":       500.000,
  "efftime":       346.850,
  "filter": "M464",
  "approx_datetime": "2025/09/24 00:35:03.14",
  "approx_airmass":       1.17860,
  "RA": 326.068,
  "dec": -8.397
 },
 {
  "seqid": "1",
  "seqnum": 14,
  "seqtot": 174,
  "expType": "object",
  "propid": "2023B-184194",
  "object": "IBIS_wide_M464_354891",
  "expTime":       500.000,
  "efftime":       350.670,
  "filter": "M464",
  "approx_datetime": "2025/09/24 00:38:31.56",
  "approx_airmass":       1.17186,
  "RA": 327.368,
  "dec": -9.561
 },
 {
  "seqid": "1",
  "seqnum": 15,
  "seqtot": 174,
  "expType": "object",
  "propid": "2023B-184194",
  "object": "IBIS_wide_M464_354897",
  "expTime":       500.000,
  "efftime":       354.880,
  "filter": "M464",
  "approx_datetime": "2025/09/24 00:42:01.90",
  "approx_airmass":       1.16636,
  "RA": 326.998,
  "dec": -8.975
 },
 {
  "seqid": "1",
  "seqnum": 16,
  "seqtot": 174,
  "expType": "object",
  "propid": "2023B-184194",
  "object": "IBIS_wide_M464_354889",
  "expTime":       500.000,
  "efftime":       337.820,
  "filter": "M464",
  "approx_datetime": "2025/09/24 00:45:34.34",
  "approx_airmass":       1.15906,
  "RA": 328.205,
  "dec": -10.131
 },
 {
  "seqid": "1",
  "seqnum": 17,
  "seqtot": 174,
  "expType": "object",
  "propid": "2023B-184194",
  "object": "IBIS_wide_M464_357877",
  "expTime":       500.000,
  "efftime":       349.770,
  "filter": "M464",
  "approx_datetime": "2025/09/24 00:48:58.25",
  "approx_airmass":       1.15495,
  "RA": 327.819,
  "dec": -9.434
 },
 {
  "seqid": "1",
  "seqnum": 18,
  "seqtot": 174,
  "expType": "object",
  "propid": "2023B-184194",
  "object": "IBIS_wide_M464_357853",
  "expTime":       500.000,
  "efftime":       334.020,
  "filter": "M464",
  "approx_datetime": "2025/09/24 00:52:28.13",
  "approx_airmass":       1.14910,
  "RA": 329.084,
  "dec": -10.509
 },
 {
  "seqid": "1",
  "seqnum": 19,
  "seqtot": 174,
  "expType": "object",
  "propid": "2023B-184194",
  "object": "IBIS_wide_M464_357875",
  "expTime":       500.000,
  "efftime":       336.580,
  "filter": "M464",
  "approx_datetime": "2025/09/24 00:55:50.14",
  "approx_airmass":       1.14344,
  "RA": 328.589,
  "dec": -9.948
 },
 {
  "seqid": "1",
  "seqnum": 20,
  "seqtot": 174,
  "expType": "object",
  "propid": "2023B-184194",
  "object": "IBIS_wide_M464_357883",
  "expTime":       500.000,
  "efftime":       354.550,
  "filter": "M464",
  "approx_datetime": "2025/09/24 00:59:13.43",
  "approx_airmass":       1.13867,
  "RA": 327.286,
  "dec": -8.701
 },
 {
  "seqid": "1",
  "seqnum": 21,
  "seqtot": 174,
  "expType": "object",
  "propid": "2023B-184194",
  "object": "IBIS_wide_M464_354868",
  "expTime":       500.000,
  "efftime":       339.080,
  "filter": "M464",
  "approx_datetime": "2025/09/24 01:02:45.71",
  "approx_airmass":       1.13528,
  "RA": 329.541,
  "dec": -10.261
 },
 {
  "seqid": "1",
  "seqnum": 22,
  "seqtot": 174,
  "expType": "object",
  "propid": "2023B-184194",
  "object": "IBIS_wide_M464_354892",
  "expTime":       500.000,
  "efftime":       350.400,
  "filter": "M464",
  "approx_datetime": "2025/09/24 01:06:10.25",
  "approx_airmass":       1.13077,
  "RA": 328.222,
  "dec": -9.021
 },
 {
  "seqid": "1",
  "seqnum": 23,
  "seqtot": 174,
  "expType": "object",
  "propid": "2023B-184194",
  "object": "IBIS_wide_M464_354890",
  "expTime":       500.000,
  "efftime":       339.400,
  "filter": "M464",
  "approx_datetime": "2025/09/24 01:09:40.45",
  "approx_airmass":       1.12625,
  "RA": 328.992,
  "dec": -9.494
 },
 {
  "seqid": "1",
  "seqnum": 24,
  "seqtot": 174,
  "expType": "object",
  "propid": "2023B-184194",
  "object": "IBIS_wide_M464_354898",
  "expTime":       500.000,
  "efftime":       353.130,
  "filter": "M464",
  "approx_datetime": "2025/09/24 01:13:05.15",
  "approx_airmass":       1.12150,
  "RA": 327.419,
  "dec": -8.338
 },
 {
  "seqid": "1",
  "seqnum": 25,
  "seqtot": 174,
  "expType": "object",
  "propid": "2023B-184194",
  "object": "IBIS_wide_M464_357852",
  "expTime":       500.000,
  "efftime":       347.040,
  "filter": "M464",
  "approx_datetime": "2025/09/24 01:16:36.71",
  "approx_airmass":       1.11705,
  "RA": 330.661,
  "dec": -10.629
 },
 {
  "seqid": "1",
  "seqnum": 26,
  "seqtot": 174,
  "expType": "object",
  "propid": "2023B-184194",
  "object": "IBIS_wide_M464_357854",
  "expTime":       500.000,
  "efftime":       344.870,
  "filter": "M464",
  "approx_datetime": "2025/09/24 01:20:05.23",
  "approx_airmass":       1.11251,
  "RA": 329.820,
  "dec": -9.914
 },
 {
  "seqid": "1",
  "seqnum": 27,
  "seqtot": 174,
  "expType": "object",
  "propid": "2023B-184194",
  "object": "IBIS_wide_M464_357846",
  "expTime":       500.000,
  "efftime":       343.830,
  "filter": "M464",
  "approx_datetime": "2025/09/24 01:23:32.67",
  "approx_airmass":       1.10846,
  "RA": 331.425,
  "dec": -11.018
 },
 {
  "seqid": "1",
  "seqnum": 28,
  "seqtot": 174,
  "expType": "object",
  "propid": "2023B-184194",
  "object": "IBIS_wide_M464_357876",
  "expTime":       500.000,
  "efftime":       340.510,
  "filter": "M464",
  "approx_datetime": "2025/09/24 01:26:59.58",
  "approx_airmass":       1.10548,
  "RA": 329.285,
  "dec": -9.309
 },
 {
  "seqid": "1",
  "seqnum": 29,
  "seqtot": 174,
  "expType": "object",
  "propid": "2023B-184194",
  "object": "IBIS_wide_M464_354869",
  "expTime":       500.000,
  "efftime":       345.610,
  "filter": "M464",
  "approx_datetime": "2025/09/24 01:30:24.84",
  "approx_airmass":       1.10207,
  "RA": 332.496,
  "dec": -11.408
 },
 {
  "seqid": "1",
  "seqnum": 30,
  "seqtot": 174,
  "expType": "object",
  "propid": "2023B-184194",
  "object": "IBIS_wide_M464_357878",
  "expTime":       500.000,
  "efftime":       348.600,
  "filter": "M464",
  "approx_datetime": "2025/09/24 01:33:52.64",
  "approx_airmass":       1.09896,
  "RA": 328.503,
  "dec": -8.735
 },
 {
  "seqid": "1",
  "seqnum": 31,
  "seqtot": 174,
  "expType": "object",
  "propid": "2023B-184194",
  "object": "IBIS_wide_M464_354879",
  "expTime":       500.000,
  "efftime":       344.940,
  "filter": "M464",
  "approx_datetime": "2025/09/24 01:37:21.94",
  "approx_airmass":       1.09543,
  "RA": 330.315,
  "dec": -9.706
 },
 {
  "seqid": "1",
  "seqnum": 32,
  "seqtot": 174,
  "expType": "object",
  "propid": "2023B-184194",
  "object": "IBIS_wide_M464_354877",
  "expTime":       500.000,
  "efftime":       339.740,
  "filter": "M464",
  "approx_datetime": "2025/09/24 01:40:49.41",
  "approx_airmass":       1.09189,
  "RA": 331.068,
  "dec": -10.125
 },
 {
  "seqid": "1",
  "seqnum": 33,
  "seqtot": 174,
  "expType": "object",
  "propid": "2023B-184194",
  "object": "IBIS_wide_M464_357855",
  "expTime":       500.000,
  "efftime":       342.620,
  "filter": "M464",
  "approx_datetime": "2025/09/24 01:44:14.28",
  "approx_airmass":       1.08944,
  "RA": 332.782,
  "dec": -10.988
 },
 {
  "seqid": "1",
  "seqnum": 34,
  "seqtot": 174,
  "expType": "object",
  "propid": "2023B-184194",
  "object": "IBIS_wide_M464_357857",
  "expTime":       500.000,
  "efftime":       338.070,
  "filter": "M464",
  "approx_datetime": "2025/09/24 01:47:40.59",
  "approx_airmass":       1.08600,
  "RA": 332.100,
  "dec": -10.566
 },
 {
  "seqid": "1",
  "seqnum": 35,
  "seqtot": 174,
  "expType": "object",
  "propid": "2023B-184194",
  "object": "IBIS_wide_M464_354812",
  "expTime":       500.000,
  "efftime":       357.080,
  "filter": "M464",
  "approx_datetime": "2025/09/24 01:51:04.63",
  "approx_airmass":       1.08377,
  "RA": 333.848,
  "dec": -11.417
 },
 {
  "seqid": "1",
  "seqnum": 36,
  "seqtot": 174,
  "expType": "object",
  "propid": "2023B-184194",
  "object": "IBIS_wide_M464_354870",
  "expTime":       500.000,
  "efftime":       348.880,
  "filter": "M464",
  "approx_datetime": "2025/09/24 01:54:38.17",
  "approx_airmass":       1.08174,
  "RA": 333.149,
  "dec": -10.804
 },
 {
  "seqid": "1",
  "seqnum": 37,
  "seqtot": 174,
  "expType": "object",
  "propid": "2023B-184194",
  "object": "IBIS_wide_M464_357798",
  "expTime":       500.000,
  "efftime":       358.270,
  "filter": "M464",
  "approx_datetime": "2025/09/24 01:58:07.61",
  "approx_airmass":       1.07897,
  "RA": 334.356,
  "dec": -11.396
 },
 {
  "seqid": "1",
  "seqnum": 38,
  "seqtot": 174,
  "expType": "object",
  "propid": "2023B-184194",
  "object": "IBIS_wide_M464_357856",
  "expTime":       500.000,
  "efftime":       360.350,
  "filter": "M464",
  "approx_datetime": "2025/09/24 02:01:41.74",
  "approx_airmass":       1.07752,
  "RA": 333.645,
  "dec": -10.779
 },
 {
  "seqid": "1",
  "seqnum": 39,
  "seqtot": 174,
  "expType": "object",
  "propid": "2023B-184194",
  "object": "IBIS_wide_M464_354872",
  "expTime":       500.000,
  "efftime":       340.710,
  "filter": "M464",
  "approx_datetime": "2025/09/24 02:05:16.92",
  "approx_airmass":       1.07557,
  "RA": 332.400,
  "dec": -10.148
 },
 {
  "seqid": "1",
  "seqnum": 40,
  "seqtot": 174,
  "expType": "object",
  "propid": "2023B-184194",
  "object": "IBIS_wide_M464_354813",
  "expTime":       500.000,
  "efftime":       353.760,
  "filter": "M464",
  "approx_datetime": "2025/09/24 02:08:42.27",
  "approx_airmass":       1.07369,
  "RA": 335.230,
  "dec": -11.269
 },
 {
  "seqid": "1",
  "seqnum": 41,
  "seqtot": 174,
  "expType": "object",
  "propid": "2023B-184194",
  "object": "IBIS_wide_M464_354806",
  "expTime":       500.000,
  "efftime":       376.520,
  "filter": "M464",
  "approx_datetime": "2025/09/24 02:12:14.15",
  "approx_airmass":       1.07149,
  "RA": 337.205,
  "dec": -12.174
 },
 {
  "seqid": "1",
  "seqnum": 42,
  "seqtot": 174,
  "expType": "object",
  "propid": "2023B-184194",
  "object": "IBIS_wide_M464_357793",
  "expTime":       500.000,
  "efftime":       355.700,
  "filter": "M464",
  "approx_datetime": "2025/09/24 02:15:57.41",
  "approx_airmass":       1.06867,
  "RA": 336.360,
  "dec": -11.721
 },
 {
  "seqid": "1",
  "seqnum": 43,
  "seqtot": 174,
  "expType": "object",
  "propid": "2023B-184194",
  "object": "IBIS_wide_M464_357799",
  "expTime":       500.000,
  "efftime":       351.660,
  "filter": "M464",
  "approx_datetime": "2025/09/24 02:19:30.26",
  "approx_airmass":       1.06811,
  "RA": 335.675,
  "dec": -11.147
 },
 {
  "seqid": "1",
  "seqnum": 44,
  "seqtot": 174,
  "expType": "object",
  "propid": "2023B-184194",
  "object": "IBIS_wide_M464_357770",
  "expTime":       500.000,
  "efftime":       395.480,
  "filter": "M464",
  "approx_datetime": "2025/09/24 02:23:01.09",
  "approx_airmass":       1.06634,
  "RA": 338.604,
  "dec": -12.320
 },
 {
  "seqid": "1",
  "seqnum": 45,
  "seqtot": 174,
  "expType": "object",
  "propid": "2023B-184194",
  "object": "IBIS_wide_M464_354808",
  "expTime":       500.000,
  "efftime":       356.890,
  "filter": "M464",
  "approx_datetime": "2025/09/24 02:26:53.83",
  "approx_airmass":       1.06407,
  "RA": 336.659,
  "dec": -11.457
 },
 {
  "seqid": "1",
  "seqnum": 46,
  "seqtot": 174,
  "expType": "object",
  "propid": "2023B-184194",
  "object": "IBIS_wide_M464_357792",
  "expTime":       500.000,
  "efftime":       375.900,
  "filter": "M464",
  "approx_datetime": "2025/09/24 02:30:27.28",
  "approx_airmass":       1.06255,
  "RA": 337.663,
  "dec": -11.738
 },
 {
  "seqid": "1",
  "seqnum": 47,
  "seqtot": 174,
  "expType": "object",
  "propid": "2023B-184194",
  "object": "IBIS_wide_M464_355090",
  "expTime":       500.000,
  "efftime":       404.030,
  "filter": "M464",
  "approx_datetime": "2025/09/24 02:34:10.23",
  "approx_airmass":       1.05995,
  "RA": 340.134,
  "dec": -12.782
 },
 {
  "seqid": "1",
  "seqnum": 48,
  "seqtot": 174,
  "expType": "object",
  "propid": "2023B-184194",
  "object": "IBIS_wide_M464_355091",
  "expTime":       500.000,
  "efftime":       398.260,
  "filter": "M464",
  "approx_datetime": "2025/09/24 02:38:07.24",
  "approx_airmass":       1.05897,
  "RA": 338.693,
  "dec": -12.015
 },
 {
  "seqid": "1",
  "seqnum": 49,
  "seqtot": 174,
  "expType": "object",
  "propid": "2023B-184194",
  "object": "IBIS_wide_M464_355084",
  "expTime":       500.000,
  "efftime":       407.980,
  "filter": "M464",
  "approx_datetime": "2025/09/24 02:42:01.37",
  "approx_airmass":       1.05899,
  "RA": 340.751,
  "dec": -12.387
 },
 {
  "seqid": "1",
  "seqnum": 50,
  "seqtot": 174,
  "expType": "object",
  "propid": "2023B-184194",
  "object": "IBIS_wide_M464_355113",
  "expTime":       500.000,
  "efftime":       391.710,
  "filter": "M464",
  "approx_datetime": "2025/09/24 02:46:00.36",
  "approx_airmass":       1.05814,
  "RA": 338.430,
  "dec": -11.557
 },
 {
  "seqid": "1",
  "seqnum": 51,
  "seqtot": 174,
  "expType": "object",
  "propid": "2023B-184194",
  "object": "IBIS_wide_M464_358070",
  "expTime":       500.000,
  "efftime":       388.840,
  "filter": "M464",
  "approx_datetime": "2025/09/24 02:49:51.22",
  "approx_airmass":       1.05628,
  "RA": 341.228,
  "dec": -12.332
 },
 {
  "seqid": "1",
  "seqnum": 52,
  "seqtot": 174,
  "expType": "object",
  "propid": "2023B-184194",
  "object": "IBIS_wide_M464_358075",
  "expTime":       500.000,
  "efftime":       432.620,
  "filter": "M464",
  "approx_datetime": "2025/09/24 02:53:40.64",
  "approx_airmass":       1.05592,
  "RA": 339.591,
  "dec": -11.768
 },
 {
  "seqid": "1",
  "seqnum": 53,
  "seqtot": 174,
  "expType": "object",
  "propid": "2023B-184194",
  "object": "IBIS_wide_M464_355087",
  "expTime":       500.000,
  "efftime":       377.120,
  "filter": "M464",
  "approx_datetime": "2025/09/24 02:57:51.95",
  "approx_airmass":       1.05526,
  "RA": 341.480,
  "dec": -12.042
 },
 {
  "seqid": "1",
  "seqnum": 54,
  "seqtot": 174,
  "expType": "object",
  "propid": "2023B-184194",
  "object": "IBIS_wide_M464_358076",
  "expTime":       500.000,
  "efftime":       429.570,
  "filter": "M464",
  "approx_datetime": "2025/09/24 03:01:35.51",
  "approx_airmass":       1.05536,
  "RA": 340.472,
  "dec": -11.692
 },
 {
  "seqid": "1",
  "seqnum": 55,
  "seqtot": 174,
  "expType": "object",
  "propid": "2023B-184194",
  "object": "IBIS_wide_M464_357986",
  "expTime":       500.000,
  "efftime":       343.380,
  "filter": "M464",
  "approx_datetime": "2025/09/24 03:05:45.29",
  "approx_airmass":       1.05396,
  "RA": 343.878,
  "dec": -12.355
 },
 {
  "seqid": "1",
  "seqnum": 56,
  "seqtot": 174,
  "expType": "object",
  "propid": "2023B-184194",
  "object": "IBIS_wide_M464_355086",
  "expTime":       500.000,
  "efftime":       351.830,
  "filter": "M464",
  "approx_datetime": "2025/09/24 03:09:11.98",
  "approx_airmass":       1.05385,
  "RA": 342.868,
  "dec": -12.006
 },
 {
  "seqid": "1",
  "seqnum": 57,
  "seqtot": 174,
  "expType": "object",
  "propid": "2023B-184194",
  "object": "IBIS_wide_M464_358072",
  "expTime":       500.000,
  "efftime":       346.740,
  "filter": "M464",
  "approx_datetime": "2025/09/24 03:12:42.90",
  "approx_airmass":       1.05417,
  "RA": 343.330,
  "dec": -11.895
 },
 {
  "seqid": "1",
  "seqnum": 58,
  "seqtot": 174,
  "expType": "object",
  "propid": "2023B-184194",
  "object": "IBIS_wide_M464_355099",
  "expTime":       500.000,
  "efftime":       353.730,
  "filter": "M464",
  "approx_datetime": "2025/09/24 03:16:11.27",
  "approx_airmass":       1.05555,
  "RA": 342.975,
  "dec": -11.548
 },
 {
  "seqid": "1",
  "seqnum": 59,
  "seqtot": 174,
  "expType": "object",
  "propid": "2023B-184194",
  "object": "IBIS_wide_M464_357997",
  "expTime":       500.000,
  "efftime":       346.840,
  "filter": "M464",
  "approx_datetime": "2025/09/24 03:19:43.13",
  "approx_airmass":       1.05500,
  "RA": 344.722,
  "dec": -11.715
 },
 {
  "seqid": "1",
  "seqnum": 60,
  "seqtot": 174,
  "expType": "object",
  "propid": "2023B-184194",
  "object": "IBIS_wide_M464_357996",
  "expTime":       500.000,
  "efftime":       341.270,
  "filter": "M464",
  "approx_datetime": "2025/09/24 03:23:11.55",
  "approx_airmass":       1.05527,
  "RA": 346.159,
  "dec": -11.743
 },
 {
  "seqid": "1",
  "seqnum": 61,
  "seqtot": 174,
  "expType": "object",
  "propid": "2023B-184194",
  "object": "IBIS_wide_M464_355012",
  "expTime":       500.000,
  "efftime":       348.010,
  "filter": "M464",
  "approx_datetime": "2025/09/24 03:26:37.19",
  "approx_airmass":       1.05616,
  "RA": 345.245,
  "dec": -11.429
 },
 {
  "seqid": "1",
  "seqnum": 62,
  "seqtot": 174,
  "expType": "object",
  "propid": "2023B-184194",
  "object": "IBIS_wide_M464_357998",
  "expTime":       500.000,
  "efftime":       346.750,
  "filter": "M464",
  "approx_datetime": "2025/09/24 03:30:06.19",
  "approx_airmass":       1.05784,
  "RA": 345.311,
  "dec": -11.134
 },
 {
  "seqid": "1",
  "seqnum": 63,
  "seqtot": 174,
  "expType": "object",
  "propid": "2023B-184194",
  "object": "IBIS_wide_M464_355014",
  "expTime":       500.000,
  "efftime":       330.160,
  "filter": "M464",
  "approx_datetime": "2025/09/24 03:33:34.57",
  "approx_airmass":       1.05934,
  "RA": 347.211,
  "dec": -10.941
 },
 {
  "seqid": "1",
  "seqnum": 64,
  "seqtot": 174,
  "expType": "object",
  "propid": "2023B-184194",
  "object": "IBIS_wide_M464_355015",
  "expTime":       500.000,
  "efftime":       346.630,
  "filter": "M464",
  "approx_datetime": "2025/09/24 03:36:54.65",
  "approx_airmass":       1.06104,
  "RA": 345.607,
  "dec": -10.660
 },
 {
  "seqid": "1",
  "seqnum": 65,
  "seqtot": 174,
  "expType": "object",
  "propid": "2023B-184194",
  "object": "IBIS_wide_M464_358001",
  "expTime":       500.000,
  "efftime":       343.740,
  "filter": "M464",
  "approx_datetime": "2025/09/24 03:40:22.96",
  "approx_airmass":       1.06171,
  "RA": 346.180,
  "dec": -10.574
 },
 {
  "seqid": "1",
  "seqnum": 66,
  "seqtot": 174,
  "expType": "object",
  "propid": "2023B-184194",
  "object": "IBIS_wide_M464_358000",
  "expTime":       500.000,
  "efftime":       330.160,
  "filter": "M464",
  "approx_datetime": "2025/09/24 03:43:49.83",
  "approx_airmass":       1.06226,
  "RA": 347.503,
  "dec": -10.468
 },
 {
  "seqid": "1",
  "seqnum": 67,
  "seqtot": 174,
  "expType": "object",
  "propid": "2023B-184194",
  "object": "IBIS_wide_M464_355052",
  "expTime":       500.000,
  "efftime":       322.320,
  "filter": "M464",
  "approx_datetime": "2025/09/24 03:47:09.91",
  "approx_airmass":       1.06312,
  "RA": 349.219,
  "dec": -10.322
 },
 {
  "seqid": "1",
  "seqnum": 68,
  "seqtot": 174,
  "expType": "object",
  "propid": "2023B-184194",
  "object": "IBIS_wide_M464_355053",
  "expTime":       500.000,
  "efftime":       321.380,
  "filter": "M464",
  "approx_datetime": "2025/09/24 03:50:26.07",
  "approx_airmass":       1.06502,
  "RA": 350.826,
  "dec": -10.055
 },
 {
  "seqid": "1",
  "seqnum": 69,
  "seqtot": 174,
  "expType": "object",
  "propid": "2023B-184194",
  "object": "IBIS_wide_M464_358038",
  "expTime":       500.000,
  "efftime":       321.820,
  "filter": "M464",
  "approx_datetime": "2025/09/24 03:53:41.76",
  "approx_airmass":       1.06653,
  "RA": 349.653,
  "dec": -9.852
 },
 {
  "seqid": "1",
  "seqnum": 70,
  "seqtot": 174,
  "expType": "object",
  "propid": "2023B-184194",
  "object": "IBIS_wide_M464_358043",
  "expTime":       500.000,
  "efftime":       332.340,
  "filter": "M464",
  "approx_datetime": "2025/09/24 03:56:57.67",
  "approx_airmass":       1.06762,
  "RA": 348.315,
  "dec": -9.904
 },
 {
  "seqid": "1",
  "seqnum": 71,
  "seqtot": 174,
  "expType": "object",
  "propid": "2023B-184194",
  "object": "IBIS_wide_M464_355054",
  "expTime":       500.000,
  "efftime":       324.350,
  "filter": "M464",
  "approx_datetime": "2025/09/24 04:00:18.84",
  "approx_airmass":       1.06825,
  "RA": 351.426,
  "dec": -9.599
 },
 {
  "seqid": "1",
  "seqnum": 72,
  "seqtot": 174,
  "expType": "object",
  "propid": "2023B-184194",
  "object": "IBIS_wide_M464_358041",
  "expTime":       500.000,
  "efftime":       322.070,
  "filter": "M464",
  "approx_datetime": "2025/09/24 04:03:36.02",
  "approx_airmass":       1.07010,
  "RA": 350.303,
  "dec": -9.505
 },
 {
  "seqid": "1",
  "seqnum": 73,
  "seqtot": 174,
  "expType": "object",
  "propid": "2023B-184194",
  "object": "IBIS_wide_M464_358040",
  "expTime":       500.000,
  "efftime":       325.110,
  "filter": "M464",
  "approx_datetime": "2025/09/24 04:06:52.05",
  "approx_airmass":       1.07101,
  "RA": 351.723,
  "dec": -9.307
 },
 {
  "seqid": "1",
  "seqnum": 74,
  "seqtot": 174,
  "expType": "object",
  "propid": "2023B-184194",
  "object": "IBIS_wide_M464_355044",
  "expTime":       500.000,
  "efftime":       317.230,
  "filter": "M464",
  "approx_datetime": "2025/09/24 04:10:09.61",
  "approx_airmass":       1.07248,
  "RA": 353.553,
  "dec": -9.022
 },
 {
  "seqid": "1",
  "seqnum": 75,
  "seqtot": 174,
  "expType": "object",
  "propid": "2023B-184194",
  "object": "IBIS_wide_M464_358051",
  "expTime":       500.000,
  "efftime":       323.670,
  "filter": "M464",
  "approx_datetime": "2025/09/24 04:13:23.22",
  "approx_airmass":       1.07357,
  "RA": 352.022,
  "dec": -9.123
 },
 {
  "seqid": "1",
  "seqnum": 76,
  "seqtot": 174,
  "expType": "object",
  "propid": "2023B-184194",
  "object": "IBIS_wide_M464_358030",
  "expTime":       500.000,
  "efftime":       317.800,
  "filter": "M464",
  "approx_datetime": "2025/09/24 04:16:40.06",
  "approx_airmass":       1.07528,
  "RA": 353.885,
  "dec": -8.750
 },
 {
  "seqid": "1",
  "seqnum": 77,
  "seqtot": 174,
  "expType": "object",
  "propid": "2023B-184194",
  "object": "IBIS_wide_M464_355065",
  "expTime":       500.000,
  "efftime":       320.040,
  "filter": "M464",
  "approx_datetime": "2025/09/24 04:19:53.96",
  "approx_airmass":       1.07808,
  "RA": 352.478,
  "dec": -8.717
 },
 {
  "seqid": "1",
  "seqnum": 78,
  "seqtot": 174,
  "expType": "object",
  "propid": "2023B-184194",
  "object": "IBIS_wide_M464_358032",
  "expTime":       500.000,
  "efftime":       318.060,
  "filter": "M464",
  "approx_datetime": "2025/09/24 04:23:08.98",
  "approx_airmass":       1.07960,
  "RA": 356.025,
  "dec": -8.123
 },
 {
  "seqid": "1",
  "seqnum": 79,
  "seqtot": 174,
  "expType": "object",
  "propid": "2023B-184194",
  "object": "IBIS_wide_M464_355047",
  "expTime":       500.000,
  "efftime":       320.350,
  "filter": "M464",
  "approx_datetime": "2025/09/24 04:26:23.01",
  "approx_airmass":       1.08114,
  "RA": 354.142,
  "dec": -8.303
 },
 {
  "seqid": "1",
  "seqnum": 80,
  "seqtot": 174,
  "expType": "object",
  "propid": "2023B-184194",
  "object": "IBIS_wide_M464_355216",
  "expTime":       500.000,
  "efftime":       318.570,
  "filter": "M464",
  "approx_datetime": "2025/09/24 04:29:38.18",
  "approx_airmass":       1.08388,
  "RA": 356.863,
  "dec": -7.651
 },
 {
  "seqid": "1",
  "seqnum": 81,
  "seqtot": 174,
  "expType": "object",
  "propid": "2023B-184194",
  "object": "IBIS_wide_M464_358033",
  "expTime":       500.000,
  "efftime":       323.730,
  "filter": "M464",
  "approx_datetime": "2025/09/24 04:32:52.47",
  "approx_airmass":       1.08610,
  "RA": 354.563,
  "dec": -7.922
 },
 {
  "seqid": "1",
  "seqnum": 82,
  "seqtot": 174,
  "expType": "object",
  "propid": "2023B-184194",
  "object": "IBIS_wide_M464_355214",
  "expTime":       500.000,
  "efftime":       341.190,
  "filter": "M464",
  "approx_datetime": "2025/09/24 04:36:09.33",
  "approx_airmass":       1.08702,
  "RA": 358.586,
  "dec": -7.245
 },
 {
  "seqid": "1",
  "seqnum": 83,
  "seqtot": 174,
  "expType": "object",
  "propid": "2023B-184194",
  "object": "IBIS_wide_M464_358202",
  "expTime":       500.000,
  "efftime":       316.480,
  "filter": "M464",
  "approx_datetime": "2025/09/24 04:39:34.93",
  "approx_airmass":       1.08953,
  "RA": 356.513,
  "dec": -7.427
 },
 {
  "seqid": "1",
  "seqnum": 84,
  "seqtot": 174,
  "expType": "object",
  "propid": "2023B-184194",
  "object": "IBIS_wide_M464_358203",
  "expTime":       500.000,
  "efftime":       328.890,
  "filter": "M464",
  "approx_datetime": "2025/09/24 04:42:48.17",
  "approx_airmass":       1.09120,
  "RA": 358.206,
  "dec": -7.037
 },
 {
  "seqid": "1",
  "seqnum": 85,
  "seqtot": 174,
  "expType": "object",
  "propid": "2023B-184194",
  "object": "IBIS_wide_M464_358200",
  "expTime":       500.000,
  "efftime":       331.280,
  "filter": "M464",
  "approx_datetime": "2025/09/24 04:46:07.61",
  "approx_airmass":       1.09279,
  "RA": 358.782,
  "dec": -6.893
 },
 {
  "seqid": "1",
  "seqnum": 86,
  "seqtot": 174,
  "expType": "object",
  "propid": "2023B-184194",
  "object": "IBIS_wide_M464_355217",
  "expTime":       500.000,
  "efftime":       316.780,
  "filter": "M464",
  "approx_datetime": "2025/09/24 04:49:28.25",
  "approx_airmass":       1.09565,
  "RA": 357.047,
  "dec": -7.180
 },
 {
  "seqid": "1",
  "seqnum": 87,
  "seqtot": 174,
  "expType": "object",
  "propid": "2023B-184194",
  "object": "IBIS_wide_M464_355220",
  "expTime":       500.000,
  "efftime":       318.410,
  "filter": "M464",
  "approx_datetime": "2025/09/24 04:52:41.64",
  "approx_airmass":       1.10127,
  "RA": 357.558,
  "dec": -6.596
 },
 {
  "seqid": "1",
  "seqnum": 88,
  "seqtot": 174,
  "expType": "object",
  "propid": "2023B-184194",
  "object": "IBIS_wide_M464_358206",
  "expTime":       500.000,
  "efftime":       320.910,
  "filter": "M464",
  "approx_datetime": "2025/09/24 04:55:55.85",
  "approx_airmass":       1.10565,
  "RA": 358.018,
  "dec": -6.193
 },
 {
  "seqid": "1",
  "seqnum": 89,
  "seqtot": 174,
  "expType": "object",
  "propid": "2023B-184194",
  "object": "IBIS_wide_M464_355221",
  "expTime":       500.000,
  "efftime":       321.600,
  "filter": "M464",
  "approx_datetime": "2025/09/24 04:59:11.30",
  "approx_airmass":       1.10833,
  "RA": 358.455,
  "dec": -6.006
 },
 {
  "seqid": "1",
  "seqnum": 90,
  "seqtot": 174,
  "expType": "object",
  "propid": "2023B-184194",
  "object": "IBIS_wide_M464_358207",
  "expTime":       500.000,
  "efftime":       321.260,
  "filter": "M464",
  "approx_datetime": "2025/09/24 05:02:27.10",
  "approx_airmass":       1.11149,
  "RA": 358.908,
  "dec": -5.769
 },
 {
  "seqid": "1",
  "seqnum": 91,
  "seqtot": 174,
  "expType": "object",
  "propid": "2023B-184194",
  "object": "IBIS_wide_M464_358210",
  "expTime":       500.000,
  "efftime":       320.710,
  "filter": "M464",
  "approx_datetime": "2025/09/24 05:05:42.73",
  "approx_airmass":       1.11793,
  "RA": 359.292,
  "dec": -5.205
 },
 {
  "seqid": "1",
  "seqnum": 92,
  "seqtot": 174,
  "expType": "object",
  "propid": "2023B-184194",
  "object": "IBIS_wide_M464_300866",
  "expTime":       500.000,
  "efftime":       320.840,
  "filter": "M464",
  "approx_datetime": "2025/09/24 05:08:58.09",
  "approx_airmass":       1.03832,
  "RA": 7.671,
  "dec": -14.665
 },
 {
  "seqid": "1",
  "seqnum": 93,
  "seqtot": 174,
  "expType": "object",
  "propid": "2023B-184194",
  "object": "IBIS_wide_M464_303810",
  "expTime":       500.000,
  "efftime":       320.290,
  "filter": "M464",
  "approx_datetime": "2025/09/24 05:12:13.51",
  "approx_airmass":       1.03988,
  "RA": 5.961,
  "dec": -14.813
 },
 {
  "seqid": "1",
  "seqnum": 94,
  "seqtot": 174,
  "expType": "object",
  "propid": "2023B-184194",
  "object": "IBIS_wide_M464_303849",
  "expTime":       500.000,
  "efftime":       300.340,
  "filter": "M464",
  "approx_datetime": "2025/09/24 05:15:28.65",
  "approx_airmass":       1.04057,
  "RA": 9.705,
  "dec": -14.186
 },
 {
  "seqid": "1",
  "seqnum": 95,
  "seqtot": 174,
  "expType": "object",
  "propid": "2023B-184194",
  "object": "IBIS_wide_M464_300873",
  "expTime":       500.000,
  "efftime":       297.860,
  "filter": "M464",
  "approx_datetime": "2025/09/24 05:18:33.82",
  "approx_airmass":       1.04194,
  "RA": 11.270,
  "dec": -13.873
 },
 {
  "seqid": "1",
  "seqnum": 96,
  "seqtot": 174,
  "expType": "object",
  "propid": "2023B-184194",
  "object": "IBIS_wide_M464_303837",
  "expTime":       500.000,
  "efftime":       303.820,
  "filter": "M464",
  "approx_datetime": "2025/09/24 05:21:37.75",
  "approx_airmass":       1.04000,
  "RA": 12.518,
  "dec": -14.227
 },
 {
  "seqid": "1",
  "seqnum": 97,
  "seqtot": 174,
  "expType": "object",
  "propid": "2023B-184194",
  "object": "IBIS_wide_M464_300852",
  "expTime":       500.000,
  "efftime":       303.650,
  "filter": "M464",
  "approx_datetime": "2025/09/24 05:24:44.66",
  "approx_airmass":       1.04211,
  "RA": 12.535,
  "dec": -13.855
 },
 {
  "seqid": "1",
  "seqnum": 98,
  "seqtot": 174,
  "expType": "object",
  "propid": "2023B-184194",
  "object": "IBIS_wide_M464_300855",
  "expTime":       500.000,
  "efftime":       307.330,
  "filter": "M464",
  "approx_datetime": "2025/09/24 05:27:51.49",
  "approx_airmass":       1.04369,
  "RA": 13.449,
  "dec": -13.554
 },
 {
  "seqid": "1",
  "seqnum": 99,
  "seqtot": 174,
  "expType": "object",
  "propid": "2023B-184194",
  "object": "IBIS_wide_M464_303838",
  "expTime":       500.000,
  "efftime":       305.830,
  "filter": "M464",
  "approx_datetime": "2025/09/24 05:31:00.15",
  "approx_airmass":       1.04474,
  "RA": 13.149,
  "dec": -13.448
 },
 {
  "seqid": "1",
  "seqnum": 100,
  "seqtot": 174,
  "expType": "object",
  "propid": "2023B-184194",
  "object": "IBIS_wide_M464_300854",
  "expTime":       500.000,
  "efftime":       305.470,
  "filter": "M464",
  "approx_datetime": "2025/09/24 05:34:08.06",
  "approx_airmass":       1.04545,
  "RA": 14.789,
  "dec": -13.247
 },
 {
  "seqid": "1",
  "seqnum": 101,
  "seqtot": 174,
  "expType": "object",
  "propid": "2023B-184194",
  "object": "IBIS_wide_M464_303859",
  "expTime":       500.000,
  "efftime":       301.130,
  "filter": "M464",
  "approx_datetime": "2025/09/24 05:37:15.80",
  "approx_airmass":       1.04739,
  "RA": 11.783,
  "dec": -13.500
 },
 {
  "seqid": "1",
  "seqnum": 102,
  "seqtot": 174,
  "expType": "object",
  "propid": "2023B-184194",
  "object": "IBIS_wide_M464_303833",
  "expTime":       500.000,
  "efftime":       303.300,
  "filter": "M464",
  "approx_datetime": "2025/09/24 05:40:21.36",
  "approx_airmass":       1.03966,
  "RA": 15.087,
  "dec": -14.456
 },
 {
  "seqid": "1",
  "seqnum": 103,
  "seqtot": 174,
  "expType": "object",
  "propid": "2023B-184194",
  "object": "IBIS_wide_M464_300847",
  "expTime":       500.000,
  "efftime":       304.870,
  "filter": "M464",
  "approx_datetime": "2025/09/24 05:43:28.01",
  "approx_airmass":       1.04107,
  "RA": 14.865,
  "dec": -14.344
 },
 {
  "seqid": "1",
  "seqnum": 104,
  "seqtot": 174,
  "expType": "object",
  "propid": "2023B-184194",
  "object": "IBIS_wide_M464_303836",
  "expTime":       500.000,
  "efftime":       309.220,
  "filter": "M464",
  "approx_datetime": "2025/09/24 05:46:35.45",
  "approx_airmass":       1.04306,
  "RA": 14.048,
  "dec": -14.327
 },
 {
  "seqid": "1",
  "seqnum": 105,
  "seqtot": 174,
  "expType": "object",
  "propid": "2023B-184194",
  "object": "IBIS_wide_M464_300848",
  "expTime":       500.000,
  "efftime":       303.840,
  "filter": "M464",
  "approx_datetime": "2025/09/24 05:49:45.06",
  "approx_airmass":       1.04593,
  "RA": 15.378,
  "dec": -13.652
 },
 {
  "seqid": "1",
  "seqnum": 106,
  "seqtot": 174,
  "expType": "object",
  "propid": "2023B-184194",
  "object": "IBIS_wide_M464_304139",
  "expTime":       500.000,
  "efftime":       304.700,
  "filter": "M464",
  "approx_datetime": "2025/09/24 05:52:51.98",
  "approx_airmass":       1.04513,
  "RA": 17.279,
  "dec": -13.568
 },
 {
  "seqid": "1",
  "seqnum": 107,
  "seqtot": 174,
  "expType": "object",
  "propid": "2023B-184194",
  "object": "IBIS_wide_M464_303834",
  "expTime":       500.000,
  "efftime":       304.610,
  "filter": "M464",
  "approx_datetime": "2025/09/24 05:55:59.33",
  "approx_airmass":       1.04815,
  "RA": 15.802,
  "dec": -13.546
 },
 {
  "seqid": "1",
  "seqnum": 108,
  "seqtot": 174,
  "expType": "object",
  "propid": "2023B-184194",
  "object": "IBIS_wide_M464_301153",
  "expTime":       500.000,
  "efftime":       305.970,
  "filter": "M464",
  "approx_datetime": "2025/09/24 05:59:06.64",
  "approx_airmass":       1.04614,
  "RA": 16.861,
  "dec": -13.835
 },
 {
  "seqid": "1",
  "seqnum": 109,
  "seqtot": 174,
  "expType": "object",
  "propid": "2023B-184194",
  "object": "IBIS_wide_M464_301154",
  "expTime":       500.000,
  "efftime":       301.740,
  "filter": "M464",
  "approx_datetime": "2025/09/24 06:02:14.62",
  "approx_airmass":       1.04713,
  "RA": 18.089,
  "dec": -13.535
 },
 {
  "seqid": "1",
  "seqnum": 110,
  "seqtot": 174,
  "expType": "object",
  "propid": "2023B-184194",
  "object": "IBIS_wide_M464_301071",
  "expTime":       500.000,
  "efftime":       304.270,
  "filter": "M464",
  "approx_datetime": "2025/09/24 06:05:20.49",
  "approx_airmass":       1.04968,
  "RA": 19.100,
  "dec": -13.022
 },
 {
  "seqid": "1",
  "seqnum": 111,
  "seqtot": 174,
  "expType": "object",
  "propid": "2023B-184194",
  "object": "IBIS_wide_M464_304054",
  "expTime":       500.000,
  "efftime":       302.120,
  "filter": "M464",
  "approx_datetime": "2025/09/24 06:08:27.63",
  "approx_airmass":       1.04933,
  "RA": 18.646,
  "dec": -13.417
 },
 {
  "seqid": "1",
  "seqnum": 112,
  "seqtot": 174,
  "expType": "object",
  "propid": "2023B-184194",
  "object": "IBIS_wide_M464_304057",
  "expTime":       500.000,
  "efftime":       305.830,
  "filter": "M464",
  "approx_datetime": "2025/09/24 06:11:33.69",
  "approx_airmass":       1.05326,
  "RA": 19.147,
  "dec": -12.809
 },
 {
  "seqid": "1",
  "seqnum": 113,
  "seqtot": 174,
  "expType": "object",
  "propid": "2023B-184194",
  "object": "IBIS_wide_M464_304055",
  "expTime":       500.000,
  "efftime":       302.930,
  "filter": "M464",
  "approx_datetime": "2025/09/24 06:14:41.60",
  "approx_airmass":       1.04890,
  "RA": 19.996,
  "dec": -13.560
 },
 {
  "seqid": "1",
  "seqnum": 114,
  "seqtot": 174,
  "expType": "object",
  "propid": "2023B-184194",
  "object": "IBIS_wide_M464_304050",
  "expTime":       500.000,
  "efftime":       298.920,
  "filter": "M464",
  "approx_datetime": "2025/09/24 06:17:48.07",
  "approx_airmass":       1.04697,
  "RA": 21.560,
  "dec": -13.678
 },
 {
  "seqid": "1",
  "seqnum": 115,
  "seqtot": 174,
  "expType": "object",
  "propid": "2023B-184194",
  "object": "IBIS_wide_M464_304046",
  "expTime":       500.000,
  "efftime":       300.550,
  "filter": "M464",
  "approx_datetime": "2025/09/24 06:20:52.53",
  "approx_airmass":       1.04506,
  "RA": 20.041,
  "dec": -14.838
 },
 {
  "seqid": "1",
  "seqnum": 116,
  "seqtot": 174,
  "expType": "object",
  "propid": "2023B-184194",
  "object": "IBIS_wide_M464_301063",
  "expTime":       500.000,
  "efftime":       301.000,
  "filter": "M464",
  "approx_datetime": "2025/09/24 06:23:57.80",
  "approx_airmass":       1.04750,
  "RA": 20.289,
  "dec": -14.589
 },
 {
  "seqid": "1",
  "seqnum": 117,
  "seqtot": 174,
  "expType": "object",
  "propid": "2023B-184194",
  "object": "IBIS_wide_M464_304049",
  "expTime":       500.000,
  "efftime":       300.560,
  "filter": "M464",
  "approx_datetime": "2025/09/24 06:27:03.30",
  "approx_airmass":       1.05029,
  "RA": 20.752,
  "dec": -14.198
 },
 {
  "seqid": "1",
  "seqnum": 118,
  "seqtot": 174,
  "expType": "object",
  "propid": "2023B-184194",
  "object": "IBIS_wide_M464_301064",
  "expTime":       500.000,
  "efftime":       299.990,
  "filter": "M464",
  "approx_datetime": "2025/09/24 06:30:08.58",
  "approx_airmass":       1.05481,
  "RA": 21.018,
  "dec": -13.602
 },
 {
  "seqid": "1",
  "seqnum": 119,
  "seqtot": 174,
  "expType": "object",
  "propid": "2023B-184194",
  "object": "IBIS_wide_M464_301073",
  "expTime":       500.000,
  "efftime":       295.700,
  "filter": "M464",
  "approx_datetime": "2025/09/24 06:33:13.58",
  "approx_airmass":       1.05166,
  "RA": 22.480,
  "dec": -13.864
 },
 {
  "seqid": "1",
  "seqnum": 120,
  "seqtot": 174,
  "expType": "object",
  "propid": "2023B-184194",
  "object": "IBIS_wide_M464_304059",
  "expTime":       500.000,
  "efftime":       297.100,
  "filter": "M464",
  "approx_datetime": "2025/09/24 06:36:16.43",
  "approx_airmass":       1.05407,
  "RA": 23.108,
  "dec": -13.488
 },
 {
  "seqid": "1",
  "seqnum": 121,
  "seqtot": 174,
  "expType": "object",
  "propid": "2023B-184194",
  "object": "IBIS_wide_M464_301052",
  "expTime":       500.000,
  "efftime":       295.650,
  "filter": "M464",
  "approx_datetime": "2025/09/24 06:39:19.98",
  "approx_airmass":       1.05259,
  "RA": 23.778,
  "dec": -13.797
 },
 {
  "seqid": "1",
  "seqnum": 122,
  "seqtot": 174,
  "expType": "object",
  "propid": "2023B-184194",
  "object": "IBIS_wide_M464_304038",
  "expTime":       500.000,
  "efftime":       295.950,
  "filter": "M464",
  "approx_datetime": "2025/09/24 06:42:22.80",
  "approx_airmass":       1.05379,
  "RA": 24.312,
  "dec": -13.682
 },
 {
  "seqid": "1",
  "seqnum": 123,
  "seqtot": 174,
  "expType": "object",
  "propid": "2023B-184194",
  "object": "IBIS_wide_M464_304060",
  "expTime":       500.000,
  "efftime":       297.870,
  "filter": "M464",
  "approx_datetime": "2025/09/24 06:45:25.78",
  "approx_airmass":       1.06193,
  "RA": 23.427,
  "dec": -13.051
 },
 {
  "seqid": "1",
  "seqnum": 124,
  "seqtot": 174,
  "expType": "object",
  "propid": "2023B-184194",
  "object": "IBIS_wide_M464_301055",
  "expTime":       500.000,
  "efftime":       298.820,
  "filter": "M464",
  "approx_datetime": "2025/09/24 06:48:29.71",
  "approx_airmass":       1.06076,
  "RA": 25.016,
  "dec": -12.845
 },
 {
  "seqid": "1",
  "seqnum": 125,
  "seqtot": 174,
  "expType": "object",
  "propid": "2023B-184194",
  "object": "IBIS_wide_M464_304041",
  "expTime":       500.000,
  "efftime":       297.550,
  "filter": "M464",
  "approx_datetime": "2025/09/24 06:51:34.12",
  "approx_airmass":       1.06090,
  "RA": 24.829,
  "dec": -13.300
 },
 {
  "seqid": "1",
  "seqnum": 126,
  "seqtot": 174,
  "expType": "object",
  "propid": "2023B-184194",
  "object": "IBIS_wide_M464_301099",
  "expTime":       500.000,
  "efftime":       296.820,
  "filter": "M464",
  "approx_datetime": "2025/09/24 06:54:37.90",
  "approx_airmass":       1.06701,
  "RA": 26.197,
  "dec": -11.984
 },
 {
  "seqid": "1",
  "seqnum": 127,
  "seqtot": 174,
  "expType": "object",
  "propid": "2023B-184194",
  "object": "IBIS_wide_M464_304039",
  "expTime":       500.000,
  "efftime":       294.800,
  "filter": "M464",
  "approx_datetime": "2025/09/24 06:57:41.31",
  "approx_airmass":       1.06190,
  "RA": 25.551,
  "dec": -13.573
 },
 {
  "seqid": "1",
  "seqnum": 128,
  "seqtot": 174,
  "expType": "object",
  "propid": "2023B-184194",
  "object": "IBIS_wide_M464_301054",
  "expTime":       500.000,
  "efftime":       295.820,
  "filter": "M464",
  "approx_datetime": "2025/09/24 07:00:43.71",
  "approx_airmass":       1.06510,
  "RA": 26.072,
  "dec": -13.157
 },
 {
  "seqid": "1",
  "seqnum": 129,
  "seqtot": 174,
  "expType": "object",
  "propid": "2023B-184194",
  "object": "IBIS_wide_M464_304033",
  "expTime":       500.000,
  "efftime":       288.360,
  "filter": "M464",
  "approx_datetime": "2025/09/24 07:03:46.62",
  "approx_airmass":       1.06135,
  "RA": 26.491,
  "dec": -14.019
 },
 {
  "seqid": "1",
  "seqnum": 130,
  "seqtot": 174,
  "expType": "object",
  "propid": "2023B-184194",
  "object": "IBIS_wide_M464_304040",
  "expTime":       500.000,
  "efftime":       295.650,
  "filter": "M464",
  "approx_datetime": "2025/09/24 07:06:45.80",
  "approx_airmass":       1.07054,
  "RA": 26.438,
  "dec": -12.929
 },
 {
  "seqid": "1",
  "seqnum": 131,
  "seqtot": 174,
  "expType": "object",
  "propid": "2023B-184194",
  "object": "IBIS_wide_M464_301098",
  "expTime":       500.000,
  "efftime":       301.940,
  "filter": "M464",
  "approx_datetime": "2025/09/24 07:09:48.62",
  "approx_airmass":       1.07532,
  "RA": 27.403,
  "dec": -12.035
 },
 {
  "seqid": "1",
  "seqnum": 132,
  "seqtot": 174,
  "expType": "object",
  "propid": "2023B-184194",
  "object": "IBIS_wide_M464_301089",
  "expTime":       500.000,
  "efftime":       289.710,
  "filter": "M464",
  "approx_datetime": "2025/09/24 07:12:54.59",
  "approx_airmass":       1.06520,
  "RA": 28.122,
  "dec": -13.750
 },
 {
  "seqid": "1",
  "seqnum": 133,
  "seqtot": 174,
  "expType": "object",
  "propid": "2023B-184194",
  "object": "IBIS_wide_M464_304075",
  "expTime":       500.000,
  "efftime":       292.320,
  "filter": "M464",
  "approx_datetime": "2025/09/24 07:15:54.44",
  "approx_airmass":       1.06862,
  "RA": 28.356,
  "dec": -13.492
 },
 {
  "seqid": "1",
  "seqnum": 134,
  "seqtot": 174,
  "expType": "object",
  "propid": "2023B-184194",
  "object": "IBIS_wide_M464_301094",
  "expTime":       500.000,
  "efftime":       299.230,
  "filter": "M464",
  "approx_datetime": "2025/09/24 07:18:55.60",
  "approx_airmass":       1.07319,
  "RA": 30.209,
  "dec": -12.073
 },
 {
  "seqid": "1",
  "seqnum": 135,
  "seqtot": 174,
  "expType": "object",
  "propid": "2023B-184194",
  "object": "IBIS_wide_M464_304076",
  "expTime":       500.000,
  "efftime":       292.360,
  "filter": "M464",
  "approx_datetime": "2025/09/24 07:22:00.22",
  "approx_airmass":       1.06916,
  "RA": 29.337,
  "dec": -13.766
 },
 {
  "seqid": "1",
  "seqnum": 136,
  "seqtot": 174,
  "expType": "object",
  "propid": "2023B-184194",
  "object": "IBIS_wide_M464_305968",
  "expTime":       500.000,
  "efftime":       289.340,
  "filter": "M464",
  "approx_datetime": "2025/09/24 07:25:01.40",
  "approx_airmass":       1.07229,
  "RA": 28.789,
  "dec": -14.171
 },
 {
  "seqid": "1",
  "seqnum": 137,
  "seqtot": 174,
  "expType": "object",
  "propid": "2023B-184194",
  "object": "IBIS_wide_M464_301093",
  "expTime":       500.000,
  "efftime":       296.780,
  "filter": "M464",
  "approx_datetime": "2025/09/24 07:28:01.07",
  "approx_airmass":       1.08154,
  "RA": 29.492,
  "dec": -12.658
 },
 {
  "seqid": "1",
  "seqnum": 138,
  "seqtot": 174,
  "expType": "object",
  "propid": "2023B-184194",
  "object": "IBIS_wide_M464_305966",
  "expTime":       500.000,
  "efftime":       292.490,
  "filter": "M464",
  "approx_datetime": "2025/09/24 07:31:04.46",
  "approx_airmass":       1.07153,
  "RA": 29.779,
  "dec": -14.725
 },
 {
  "seqid": "1",
  "seqnum": 139,
  "seqtot": 174,
  "expType": "object",
  "propid": "2023B-184194",
  "object": "IBIS_wide_M464_302960",
  "expTime":       500.000,
  "efftime":       293.390,
  "filter": "M464",
  "approx_datetime": "2025/09/24 07:34:05.70",
  "approx_airmass":       1.08079,
  "RA": 29.699,
  "dec": -13.787
 },
 {
  "seqid": "1",
  "seqnum": 140,
  "seqtot": 174,
  "expType": "object",
  "propid": "2023B-184194",
  "object": "IBIS_wide_M464_305969",
  "expTime":       500.000,
  "efftime":       294.590,
  "filter": "M464",
  "approx_datetime": "2025/09/24 07:37:07.40",
  "approx_airmass":       1.08481,
  "RA": 29.943,
  "dec": -13.540
 },
 {
  "seqid": "1",
  "seqnum": 141,
  "seqtot": 174,
  "expType": "object",
  "propid": "2023B-184194",
  "object": "IBIS_wide_M464_305971",
  "expTime":       500.000,
  "efftime":       299.750,
  "filter": "M464",
  "approx_datetime": "2025/09/24 07:40:09.69",
  "approx_airmass":       1.08303,
  "RA": 31.817,
  "dec": -12.949
 },
 {
  "seqid": "1",
  "seqnum": 142,
  "seqtot": 174,
  "expType": "object",
  "propid": "2023B-184194",
  "object": "IBIS_wide_M464_302961",
  "expTime":       500.000,
  "efftime":       298.910,
  "filter": "M464",
  "approx_datetime": "2025/09/24 07:43:14.57",
  "approx_airmass":       1.08606,
  "RA": 30.914,
  "dec": -13.810
 },
 {
  "seqid": "1",
  "seqnum": 143,
  "seqtot": 174,
  "expType": "object",
  "propid": "2023B-184194",
  "object": "IBIS_wide_M464_302972",
  "expTime":       500.000,
  "efftime":       300.020,
  "filter": "M464",
  "approx_datetime": "2025/09/24 07:46:19.02",
  "approx_airmass":       1.09058,
  "RA": 32.278,
  "dec": -12.592
 },
 {
  "seqid": "1",
  "seqnum": 144,
  "seqtot": 174,
  "expType": "object",
  "propid": "2023B-184194",
  "object": "IBIS_wide_M464_305981",
  "expTime":       500.000,
  "efftime":       300.710,
  "filter": "M464",
  "approx_datetime": "2025/09/24 07:49:24.03",
  "approx_airmass":       1.09383,
  "RA": 32.672,
  "dec": -12.392
 },
 {
  "seqid": "1",
  "seqnum": 145,
  "seqtot": 174,
  "expType": "object",
  "propid": "2023B-184194",
  "object": "IBIS_wide_M464_305982",
  "expTime":       500.000,
  "efftime":       304.270,
  "filter": "M464",
  "approx_datetime": "2025/09/24 07:52:29.39",
  "approx_airmass":       1.09931,
  "RA": 33.270,
  "dec": -11.714
 },
 {
  "seqid": "1",
  "seqnum": 146,
  "seqtot": 174,
  "expType": "object",
  "propid": "2023B-184194",
  "object": "IBIS_wide_M464_305965",
  "expTime":       500.000,
  "efftime":       302.480,
  "filter": "M464",
  "approx_datetime": "2025/09/24 07:55:36.52",
  "approx_airmass":       1.09527,
  "RA": 32.390,
  "dec": -13.757
 },
 {
  "seqid": "1",
  "seqnum": 147,
  "seqtot": 174,
  "expType": "object",
  "propid": "2023B-184194",
  "object": "IBIS_wide_M464_302956",
  "expTime":       500.000,
  "efftime":       302.670,
  "filter": "M464",
  "approx_datetime": "2025/09/24 07:58:42.76",
  "approx_airmass":       1.09783,
  "RA": 32.854,
  "dec": -13.637
 },
 {
  "seqid": "1",
  "seqnum": 148,
  "seqtot": 174,
  "expType": "object",
  "propid": "2023B-184194",
  "object": "IBIS_wide_M464_302967",
  "expTime":       500.000,
  "efftime":       301.850,
  "filter": "M464",
  "approx_datetime": "2025/09/24 08:01:49.10",
  "approx_airmass":       1.10052,
  "RA": 33.373,
  "dec": -13.454
 },
 {
  "seqid": "1",
  "seqnum": 149,
  "seqtot": 174,
  "expType": "object",
  "propid": "2023B-184194",
  "object": "IBIS_wide_M464_305977",
  "expTime":       500.000,
  "efftime":       302.290,
  "filter": "M464",
  "approx_datetime": "2025/09/24 08:04:55.02",
  "approx_airmass":       1.10745,
  "RA": 34.046,
  "dec": -12.489
 },
 {
  "seqid": "1",
  "seqnum": 150,
  "seqtot": 174,
  "expType": "object",
  "propid": "2023B-184194",
  "object": "IBIS_wide_M464_305976",
  "expTime":       500.000,
  "efftime":       301.140,
  "filter": "M464",
  "approx_datetime": "2025/09/24 08:08:01.17",
  "approx_airmass":       1.11325,
  "RA": 33.353,
  "dec": -13.019
 },
 {
  "seqid": "1",
  "seqnum": 151,
  "seqtot": 174,
  "expType": "object",
  "propid": "2023B-184194",
  "object": "IBIS_wide_M464_302948",
  "expTime":       500.000,
  "efftime":       298.170,
  "filter": "M464",
  "approx_datetime": "2025/09/24 08:11:06.74",
  "approx_airmass":       1.10245,
  "RA": 35.124,
  "dec": -13.707
 },
 {
  "seqid": "1",
  "seqnum": 152,
  "seqtot": 174,
  "expType": "object",
  "propid": "2023B-184194",
  "object": "IBIS_wide_M464_302947",
  "expTime":       500.000,
  "efftime":       303.040,
  "filter": "M464",
  "approx_datetime": "2025/09/24 08:14:10.83",
  "approx_airmass":       1.10897,
  "RA": 34.304,
  "dec": -14.299
 },
 {
  "seqid": "1",
  "seqnum": 153,
  "seqtot": 174,
  "expType": "object",
  "propid": "2023B-184194",
  "object": "IBIS_wide_M464_303901",
  "expTime":       500.000,
  "efftime":       297.620,
  "filter": "M464",
  "approx_datetime": "2025/09/24 08:17:17.35",
  "approx_airmass":       1.11276,
  "RA": 35.702,
  "dec": -13.068
 },
 {
  "seqid": "1",
  "seqnum": 154,
  "seqtot": 174,
  "expType": "object",
  "propid": "2023B-184194",
  "object": "IBIS_wide_M464_309898",
  "expTime":       500.000,
  "efftime":       301.230,
  "filter": "M464",
  "approx_datetime": "2025/09/24 08:20:21.16",
  "approx_airmass":       1.11728,
  "RA": 37.059,
  "dec": -11.848
 },
 {
  "seqid": "1",
  "seqnum": 155,
  "seqtot": 174,
  "expType": "object",
  "propid": "2023B-184194",
  "object": "IBIS_wide_M464_309937",
  "expTime":       500.000,
  "efftime":       310.700,
  "filter": "M464",
  "approx_datetime": "2025/09/24 08:23:26.77",
  "approx_airmass":       1.12278,
  "RA": 38.384,
  "dec": -10.615
 },
 {
  "seqid": "1",
  "seqnum": 156,
  "seqtot": 174,
  "expType": "object",
  "propid": "2023B-184194",
  "object": "IBIS_wide_M464_300898",
  "expTime":       500.000,
  "efftime":       301.380,
  "filter": "M464",
  "approx_datetime": "2025/09/24 08:26:37.12",
  "approx_airmass":       1.11818,
  "RA": 35.652,
  "dec": -14.813
 },
 {
  "seqid": "1",
  "seqnum": 157,
  "seqtot": 174,
  "expType": "object",
  "propid": "2023B-184194",
  "object": "IBIS_wide_M464_309876",
  "expTime":       500.000,
  "efftime":       301.990,
  "filter": "M464",
  "approx_datetime": "2025/09/24 08:29:42.81",
  "approx_airmass":       1.11542,
  "RA": 36.799,
  "dec": -14.825
 },
 {
  "seqid": "1",
  "seqnum": 158,
  "seqtot": 174,
  "expType": "object",
  "propid": "2023B-184194",
  "object": "IBIS_wide_M464_306902",
  "expTime":       500.000,
  "efftime":       297.970,
  "filter": "M464",
  "approx_datetime": "2025/09/24 08:32:48.81",
  "approx_airmass":       1.12275,
  "RA": 37.407,
  "dec": -13.862
 },
 {
  "seqid": "1",
  "seqnum": 159,
  "seqtot": 174,
  "expType": "object",
  "propid": "2023B-184194",
  "object": "IBIS_wide_M464_309913",
  "expTime":       500.000,
  "efftime":       316.490,
  "filter": "M464",
  "approx_datetime": "2025/09/24 08:35:52.79",
  "approx_airmass":       1.12671,
  "RA": 39.433,
  "dec": -11.970
 },
 {
  "seqid": "1",
  "seqnum": 160,
  "seqtot": 174,
  "expType": "object",
  "propid": "2023B-184194",
  "object": "IBIS_wide_M464_306905",
  "expTime":       500.000,
  "efftime":       298.630,
  "filter": "M464",
  "approx_datetime": "2025/09/24 08:39:06.04",
  "approx_airmass":       1.13254,
  "RA": 38.089,
  "dec": -13.407
 },
 {
  "seqid": "1",
  "seqnum": 161,
  "seqtot": 174,
  "expType": "object",
  "propid": "2023B-184194",
  "object": "IBIS_wide_M464_309886",
  "expTime":       500.000,
  "efftime":       303.650,
  "filter": "M464",
  "approx_datetime": "2025/09/24 08:42:10.35",
  "approx_airmass":       1.12751,
  "RA": 38.629,
  "dec": -14.431
 },
 {
  "seqid": "1",
  "seqnum": 162,
  "seqtot": 174,
  "expType": "object",
  "propid": "2023B-184194",
  "object": "IBIS_wide_M464_309890",
  "expTime":       500.000,
  "efftime":       314.450,
  "filter": "M464",
  "approx_datetime": "2025/09/24 08:45:17.17",
  "approx_airmass":       1.13352,
  "RA": 39.869,
  "dec": -13.010
 },
 {
  "seqid": "1",
  "seqnum": 163,
  "seqtot": 174,
  "expType": "object",
  "propid": "2023B-184194",
  "object": "IBIS_wide_M464_309880",
  "expTime":       500.000,
  "efftime":       308.180,
  "filter": "M464",
  "approx_datetime": "2025/09/24 08:48:29.40",
  "approx_airmass":       1.13302,
  "RA": 39.196,
  "dec": -14.823
 },
 {
  "seqid": "1",
  "seqnum": 164,
  "seqtot": 174,
  "expType": "object",
  "propid": "2023B-184194",
  "object": "IBIS_wide_M464_309909",
  "expTime":       500.000,
  "efftime":       319.790,
  "filter": "M464",
  "approx_datetime": "2025/09/24 08:51:38.49",
  "approx_airmass":       1.13260,
  "RA": 42.958,
  "dec": -11.583
 },
 {
  "seqid": "1",
  "seqnum": 165,
  "seqtot": 174,
  "expType": "object",
  "propid": "2023B-184194",
  "object": "IBIS_wide_M464_309881",
  "expTime":       500.000,
  "efftime":       312.820,
  "filter": "M464",
  "approx_datetime": "2025/09/24 08:54:53.38",
  "approx_airmass":       1.13675,
  "RA": 40.446,
  "dec": -14.693
 },
 {
  "seqid": "1",
  "seqnum": 166,
  "seqtot": 174,
  "expType": "object",
  "propid": "2023B-184194",
  "object": "IBIS_wide_M464_309907",
  "expTime":       500.000,
  "efftime":       319.750,
  "filter": "M464",
  "approx_datetime": "2025/09/24 08:58:04.79",
  "approx_airmass":       1.13603,
  "RA": 43.349,
  "dec": -12.363
 },
 {
  "seqid": "1",
  "seqnum": 167,
  "seqtot": 174,
  "expType": "object",
  "propid": "2023B-184194",
  "object": "IBIS_wide_M464_306917",
  "expTime":       500.000,
  "efftime":       311.700,
  "filter": "M464",
  "approx_datetime": "2025/09/24 09:01:19.67",
  "approx_airmass":       1.14598,
  "RA": 41.625,
  "dec": -13.862
 },
 {
  "seqid": "1",
  "seqnum": 168,
  "seqtot": 174,
  "expType": "object",
  "propid": "2023B-184194",
  "object": "IBIS_wide_M464_306859",
  "expTime":       500.000,
  "efftime":       310.850,
  "filter": "M464",
  "approx_datetime": "2025/09/24 09:04:30.52",
  "approx_airmass":       1.14426,
  "RA": 42.164,
  "dec": -14.439
 },
 {
  "seqid": "1",
  "seqnum": 169,
  "seqtot": 174,
  "expType": "object",
  "propid": "2023B-184194",
  "object": "IBIS_wide_M464_309844",
  "expTime":       500.000,
  "efftime":       337.500,
  "filter": "M464",
  "approx_datetime": "2025/09/24 09:07:40.94",
  "approx_airmass":       1.13796,
  "RA": 43.909,
  "dec": -14.191
 },
 {
  "seqid": "1",
  "seqnum": 170,
  "seqtot": 174,
  "expType": "object",
  "propid": "2023B-184194",
  "object": "IBIS_wide_M464_306861",
  "expTime":       500.000,
  "efftime":       342.600,
  "filter": "M464",
  "approx_datetime": "2025/09/24 09:11:04.69",
  "approx_airmass":       1.14289,
  "RA": 44.142,
  "dec": -14.224
 },
 {
  "seqid": "1",
  "seqnum": 171,
  "seqtot": 174,
  "expType": "object",
  "propid": "2023B-184194",
  "object": "IBIS_wide_M464_309838",
  "expTime":       500.000,
  "efftime":       363.810,
  "filter": "M464",
  "approx_datetime": "2025/09/24 09:14:30.99",
  "approx_airmass":       1.14137,
  "RA": 44.840,
  "dec": -14.659
 },
 {
  "seqid": "1",
  "seqnum": 172,
  "seqtot": 174,
  "expType": "object",
  "propid": "2023B-184194",
  "object": "IBIS_wide_M464_306868",
  "expTime":       500.000,
  "efftime":       405.670,
  "filter": "M464",
  "approx_datetime": "2025/09/24 09:18:07.90",
  "approx_airmass":       1.14348,
  "RA": 47.166,
  "dec": -12.654
 },
 {
  "seqid": "1",
  "seqnum": 173,
  "seqtot": 174,
  "expType": "object",
  "propid": "2023B-184194",
  "object": "IBIS_wide_M464_306865",
  "expTime":       500.000,
  "efftime":       387.850,
  "filter": "M464",
  "approx_datetime": "2025/09/24 09:22:05.73",
  "approx_airmass":       1.14220,
  "RA": 47.270,
  "dec": -13.873
 }
]
