[
 {
  "seqid": "1",
  "seqnum": 0,
  "seqtot": 122,
  "expType": "object",
  "propid": "2023B-184194",
  "object": "IBIS_wide_M490_401073",
  "expTime":      800,
  "efftime":       284.190,
  "filter": "M490",
  "approx_datetime": "2025/12/16 00:59:34.00",
  "approx_airmass":       1.04783,
  "RA": 22.480,
  "dec": -13.864
 },
 {
  "seqid": "1",
  "seqnum": 1,
  "seqtot": 122,
  "expType": "object",
  "propid": "2023B-184194",
  "object": "IBIS_wide_M490_404050",
  "expTime":      800,
  "efftime":       287.100,
  "filter": "M490",
  "approx_datetime": "2025/12/16 01:02:51.39",
  "approx_airmass":       1.05247,
  "RA": 21.560,
  "dec": -13.678
 },
 {
  "seqid": "1",
  "seqnum": 2,
  "seqtot": 122,
  "expType": "object",
  "propid": "2023B-184194",
  "object": "IBIS_wide_M490_401074",
  "expTime":      800,
  "efftime":       288.660,
  "filter": "M490",
  "approx_datetime": "2025/12/16 01:06:10.45",
  "approx_airmass":       1.05541,
  "RA": 22.921,
  "dec": -12.947
 },
 {
  "seqid": "1",
  "seqnum": 3,
  "seqtot": 122,
  "expType": "object",
  "propid": "2023B-184194",
  "object": "IBIS_wide_M490_404063",
  "expTime":      800,
  "efftime":       290.260,
  "filter": "M490",
  "approx_datetime": "2025/12/16 01:09:30.40",
  "approx_airmass":       1.05872,
  "RA": 24.083,
  "dec": -12.268
 },
 {
  "seqid": "1",
  "seqnum": 4,
  "seqtot": 122,
  "expType": "object",
  "propid": "2023B-184194",
  "object": "IBIS_wide_M490_401055",
  "expTime":      800,
  "efftime":       287.010,
  "filter": "M490",
  "approx_datetime": "2025/12/16 01:12:51.26",
  "approx_airmass":       1.05510,
  "RA": 25.016,
  "dec": -12.845
 },
 {
  "seqid": "1",
  "seqnum": 5,
  "seqtot": 122,
  "expType": "object",
  "propid": "2023B-184194",
  "object": "IBIS_wide_M490_401078",
  "expTime":      800,
  "efftime":       290.410,
  "filter": "M490",
  "approx_datetime": "2025/12/16 01:16:10.27",
  "approx_airmass":       1.06267,
  "RA": 24.635,
  "dec": -12.042
 },
 {
  "seqid": "1",
  "seqnum": 6,
  "seqtot": 122,
  "expType": "object",
  "propid": "2023B-184194",
  "object": "IBIS_wide_M490_404039",
  "expTime":      800,
  "efftime":       283.390,
  "filter": "M490",
  "approx_datetime": "2025/12/16 01:19:31.22",
  "approx_airmass":       1.05350,
  "RA": 25.551,
  "dec": -13.573
 },
 {
  "seqid": "1",
  "seqnum": 7,
  "seqtot": 122,
  "expType": "object",
  "propid": "2023B-184194",
  "object": "IBIS_wide_M490_401054",
  "expTime":      800,
  "efftime":       284.300,
  "filter": "M490",
  "approx_datetime": "2025/12/16 01:22:48.15",
  "approx_airmass":       1.05659,
  "RA": 26.072,
  "dec": -13.157
 },
 {
  "seqid": "1",
  "seqnum": 8,
  "seqtot": 122,
  "expType": "object",
  "propid": "2023B-184194",
  "object": "IBIS_wide_M490_404040",
  "expTime":      800,
  "efftime":       284.160,
  "filter": "M490",
  "approx_datetime": "2025/12/16 01:26:05.61",
  "approx_airmass":       1.05909,
  "RA": 26.438,
  "dec": -12.929
 },
 {
  "seqid": "1",
  "seqnum": 9,
  "seqtot": 122,
  "expType": "object",
  "propid": "2023B-184194",
  "object": "IBIS_wide_M490_404077",
  "expTime":      800,
  "efftime":       284.350,
  "filter": "M490",
  "approx_datetime": "2025/12/16 01:29:22.99",
  "approx_airmass":       1.05879,
  "RA": 27.338,
  "dec": -12.947
 },
 {
  "seqid": "1",
  "seqnum": 10,
  "seqtot": 122,
  "expType": "object",
  "propid": "2023B-184194",
  "object": "IBIS_wide_M490_404084",
  "expTime":      800,
  "efftime":       288.540,
  "filter": "M490",
  "approx_datetime": "2025/12/16 01:32:40.47",
  "approx_airmass":       1.06202,
  "RA": 28.182,
  "dec": -12.396
 },
 {
  "seqid": "1",
  "seqnum": 11,
  "seqtot": 122,
  "expType": "object",
  "propid": "2023B-184194",
  "object": "IBIS_wide_M490_401091",
  "expTime":      800,
  "efftime":       283.880,
  "filter": "M490",
  "approx_datetime": "2025/12/16 01:36:00.35",
  "approx_airmass":       1.06134,
  "RA": 27.893,
  "dec": -13.037
 },
 {
  "seqid": "1",
  "seqnum": 12,
  "seqtot": 122,
  "expType": "object",
  "propid": "2023B-184194",
  "object": "IBIS_wide_M490_404078",
  "expTime":      800,
  "efftime":       288.500,
  "filter": "M490",
  "approx_datetime": "2025/12/16 01:39:17.57",
  "approx_airmass":       1.06632,
  "RA": 28.626,
  "dec": -12.253
 },
 {
  "seqid": "1",
  "seqnum": 13,
  "seqtot": 122,
  "expType": "object",
  "propid": "2023B-184194",
  "object": "IBIS_wide_M490_401090",
  "expTime":      800,
  "efftime":       284.000,
  "filter": "M490",
  "approx_datetime": "2025/12/16 01:42:37.43",
  "approx_airmass":       1.06319,
  "RA": 28.959,
  "dec": -13.028
 },
 {
  "seqid": "1",
  "seqnum": 14,
  "seqtot": 122,
  "expType": "object",
  "propid": "2023B-184194",
  "object": "IBIS_wide_M490_401093",
  "expTime":      800,
  "efftime":       285.170,
  "filter": "M490",
  "approx_datetime": "2025/12/16 01:45:54.71",
  "approx_airmass":       1.06632,
  "RA": 29.492,
  "dec": -12.658
 },
 {
  "seqid": "1",
  "seqnum": 15,
  "seqtot": 122,
  "expType": "object",
  "propid": "2023B-184194",
  "object": "IBIS_wide_M490_401094",
  "expTime":      800,
  "efftime":       287.370,
  "filter": "M490",
  "approx_datetime": "2025/12/16 01:49:12.67",
  "approx_airmass":       1.07029,
  "RA": 30.209,
  "dec": -12.073
 },
 {
  "seqid": "1",
  "seqnum": 16,
  "seqtot": 122,
  "expType": "object",
  "propid": "2023B-184194",
  "object": "IBIS_wide_M490_401105",
  "expTime":      800,
  "efftime":       289.830,
  "filter": "M490",
  "approx_datetime": "2025/12/16 01:52:31.88",
  "approx_airmass":       1.07490,
  "RA": 30.932,
  "dec": -11.410
 },
 {
  "seqid": "1",
  "seqnum": 17,
  "seqtot": 122,
  "expType": "object",
  "propid": "2023B-184194",
  "object": "IBIS_wide_M490_402974",
  "expTime":      800,
  "efftime":       288.000,
  "filter": "M490",
  "approx_datetime": "2025/12/16 01:55:52.50",
  "approx_airmass":       1.07135,
  "RA": 31.688,
  "dec": -12.005
 },
 {
  "seqid": "1",
  "seqnum": 18,
  "seqtot": 122,
  "expType": "object",
  "propid": "2023B-184194",
  "object": "IBIS_wide_M490_404080",
  "expTime":      800,
  "efftime":       289.990,
  "filter": "M490",
  "approx_datetime": "2025/12/16 01:59:12.07",
  "approx_airmass":       1.08068,
  "RA": 30.490,
  "dec": -11.719
 },
 {
  "seqid": "1",
  "seqnum": 19,
  "seqtot": 122,
  "expType": "object",
  "propid": "2023B-184194",
  "object": "IBIS_wide_M490_402975",
  "expTime":      800,
  "efftime":       288.260,
  "filter": "M490",
  "approx_datetime": "2025/12/16 02:02:32.78",
  "approx_airmass":       1.07960,
  "RA": 31.979,
  "dec": -11.495
 },
 {
  "seqid": "1",
  "seqnum": 20,
  "seqtot": 122,
  "expType": "object",
  "propid": "2023B-184194",
  "object": "IBIS_wide_M490_405984",
  "expTime":      800,
  "efftime":       292.440,
  "filter": "M490",
  "approx_datetime": "2025/12/16 02:05:52.50",
  "approx_airmass":       1.08256,
  "RA": 32.652,
  "dec": -11.145
 },
 {
  "seqid": "1",
  "seqnum": 21,
  "seqtot": 122,
  "expType": "object",
  "propid": "2023B-184194",
  "object": "IBIS_wide_M490_402978",
  "expTime":      800,
  "efftime":       296.980,
  "filter": "M490",
  "approx_datetime": "2025/12/16 02:09:14.61",
  "approx_airmass":       1.08685,
  "RA": 33.031,
  "dec": -10.789
 },
 {
  "seqid": "1",
  "seqnum": 22,
  "seqtot": 122,
  "expType": "object",
  "propid": "2023B-184194",
  "object": "IBIS_wide_M490_405986",
  "expTime":      800,
  "efftime":       296.400,
  "filter": "M490",
  "approx_datetime": "2025/12/16 02:12:39.31",
  "approx_airmass":       1.08316,
  "RA": 35.108,
  "dec": -10.639
 },
 {
  "seqid": "1",
  "seqnum": 23,
  "seqtot": 122,
  "expType": "object",
  "propid": "2023B-184194",
  "object": "IBIS_wide_M490_402970",
  "expTime":      800,
  "efftime":       295.200,
  "filter": "M490",
  "approx_datetime": "2025/12/16 02:16:03.68",
  "approx_airmass":       1.08159,
  "RA": 34.281,
  "dec": -11.852
 },
 {
  "seqid": "1",
  "seqnum": 24,
  "seqtot": 122,
  "expType": "object",
  "propid": "2023B-184194",
  "object": "IBIS_wide_M490_405982",
  "expTime":      800,
  "efftime":       291.910,
  "filter": "M490",
  "approx_datetime": "2025/12/16 02:19:27.37",
  "approx_airmass":       1.09081,
  "RA": 33.270,
  "dec": -11.714
 },
 {
  "seqid": "1",
  "seqnum": 25,
  "seqtot": 122,
  "expType": "object",
  "propid": "2023B-184194",
  "object": "IBIS_wide_M490_405977",
  "expTime":      800,
  "efftime":       290.130,
  "filter": "M490",
  "approx_datetime": "2025/12/16 02:22:49.17",
  "approx_airmass":       1.08605,
  "RA": 34.046,
  "dec": -12.489
 },
 {
  "seqid": "1",
  "seqnum": 26,
  "seqtot": 122,
  "expType": "object",
  "propid": "2023B-184194",
  "object": "IBIS_wide_M490_405975",
  "expTime":      800,
  "efftime":       291.740,
  "filter": "M490",
  "approx_datetime": "2025/12/16 02:26:09.96",
  "approx_airmass":       1.08816,
  "RA": 34.748,
  "dec": -12.264
 },
 {
  "seqid": "1",
  "seqnum": 27,
  "seqtot": 122,
  "expType": "object",
  "propid": "2023B-184194",
  "object": "IBIS_wide_M490_406912",
  "expTime":      800,
  "efftime":       286.610,
  "filter": "M490",
  "approx_datetime": "2025/12/16 02:29:31.67",
  "approx_airmass":       1.08506,
  "RA": 36.457,
  "dec": -12.118
 },
 {
  "seqid": "1",
  "seqnum": 28,
  "seqtot": 122,
  "expType": "object",
  "propid": "2023B-184194",
  "object": "IBIS_wide_M490_409895",
  "expTime":      800,
  "efftime":       289.010,
  "filter": "M490",
  "approx_datetime": "2025/12/16 02:32:50.45",
  "approx_airmass":       1.09180,
  "RA": 36.628,
  "dec": -11.566
 },
 {
  "seqid": "1",
  "seqnum": 29,
  "seqtot": 122,
  "expType": "object",
  "propid": "2023B-184194",
  "object": "IBIS_wide_M490_402969",
  "expTime":      800,
  "efftime":       290.100,
  "filter": "M490",
  "approx_datetime": "2025/12/16 02:36:10.59",
  "approx_airmass":       1.09761,
  "RA": 35.162,
  "dec": -12.469
 },
 {
  "seqid": "1",
  "seqnum": 30,
  "seqtot": 122,
  "expType": "object",
  "propid": "2023B-184194",
  "object": "IBIS_wide_M490_400922",
  "expTime":      800,
  "efftime":       288.990,
  "filter": "M490",
  "approx_datetime": "2025/12/16 02:39:31.37",
  "approx_airmass":       1.10289,
  "RA": 35.769,
  "dec": -11.875
 },
 {
  "seqid": "1",
  "seqnum": 31,
  "seqtot": 122,
  "expType": "object",
  "propid": "2023B-184194",
  "object": "IBIS_wide_M490_406913",
  "expTime":      800,
  "efftime":       291.740,
  "filter": "M490",
  "approx_datetime": "2025/12/16 02:42:51.50",
  "approx_airmass":       1.10367,
  "RA": 37.079,
  "dec": -11.382
 },
 {
  "seqid": "1",
  "seqnum": 32,
  "seqtot": 122,
  "expType": "object",
  "propid": "2023B-184194",
  "object": "IBIS_wide_M490_409888",
  "expTime":      800,
  "efftime":       286.390,
  "filter": "M490",
  "approx_datetime": "2025/12/16 02:46:13.21",
  "approx_airmass":       1.09222,
  "RA": 37.711,
  "dec": -13.283
 },
 {
  "seqid": "1",
  "seqnum": 33,
  "seqtot": 122,
  "expType": "object",
  "propid": "2023B-184194",
  "object": "IBIS_wide_M490_409899",
  "expTime":      800,
  "efftime":       294.410,
  "filter": "M490",
  "approx_datetime": "2025/12/16 02:49:31.86",
  "approx_airmass":       1.11062,
  "RA": 37.625,
  "dec": -11.311
 },
 {
  "seqid": "1",
  "seqnum": 34,
  "seqtot": 122,
  "expType": "object",
  "propid": "2023B-184194",
  "object": "IBIS_wide_M490_406900",
  "expTime":      800,
  "efftime":       290.950,
  "filter": "M490",
  "approx_datetime": "2025/12/16 02:52:55.10",
  "approx_airmass":       1.09065,
  "RA": 38.166,
  "dec": -14.676
 },
 {
  "seqid": "1",
  "seqnum": 35,
  "seqtot": 122,
  "expType": "object",
  "propid": "2023B-184194",
  "object": "IBIS_wide_M490_406902",
  "expTime":      800,
  "efftime":       286.240,
  "filter": "M490",
  "approx_datetime": "2025/12/16 02:56:16.35",
  "approx_airmass":       1.10524,
  "RA": 37.407,
  "dec": -13.862
 },
 {
  "seqid": "1",
  "seqnum": 36,
  "seqtot": 122,
  "expType": "object",
  "propid": "2023B-184194",
  "object": "IBIS_wide_M490_409887",
  "expTime":      800,
  "efftime":       286.740,
  "filter": "M490",
  "approx_datetime": "2025/12/16 02:59:34.92",
  "approx_airmass":       1.10938,
  "RA": 37.388,
  "dec": -14.083
 },
 {
  "seqid": "1",
  "seqnum": 37,
  "seqtot": 122,
  "expType": "object",
  "propid": "2023B-184194",
  "object": "IBIS_wide_M490_406906",
  "expTime":      800,
  "efftime":       292.980,
  "filter": "M490",
  "approx_datetime": "2025/12/16 03:02:53.77",
  "approx_airmass":       1.11463,
  "RA": 38.825,
  "dec": -12.665
 },
 {
  "seqid": "1",
  "seqnum": 38,
  "seqtot": 122,
  "expType": "object",
  "propid": "2023B-184194",
  "object": "IBIS_wide_M490_409889",
  "expTime":      800,
  "efftime":       292.490,
  "filter": "M490",
  "approx_datetime": "2025/12/16 03:06:16.19",
  "approx_airmass":       1.11290,
  "RA": 39.127,
  "dec": -13.467
 },
 {
  "seqid": "1",
  "seqnum": 39,
  "seqtot": 122,
  "expType": "object",
  "propid": "2023B-184194",
  "object": "IBIS_wide_M490_409883",
  "expTime":      800,
  "efftime":       295.400,
  "filter": "M490",
  "approx_datetime": "2025/12/16 03:09:38.33",
  "approx_airmass":       1.11231,
  "RA": 39.688,
  "dec": -13.854
 },
 {
  "seqid": "1",
  "seqnum": 40,
  "seqtot": 122,
  "expType": "object",
  "propid": "2023B-184194",
  "object": "IBIS_wide_M490_409905",
  "expTime":      800,
  "efftime":       304.020,
  "filter": "M490",
  "approx_datetime": "2025/12/16 03:13:02.13",
  "approx_airmass":       1.11440,
  "RA": 41.261,
  "dec": -12.802
 },
 {
  "seqid": "1",
  "seqnum": 41,
  "seqtot": 122,
  "expType": "object",
  "propid": "2023B-184194",
  "object": "IBIS_wide_M490_409912",
  "expTime":      800,
  "efftime":       303.450,
  "filter": "M490",
  "approx_datetime": "2025/12/16 03:16:30.85",
  "approx_airmass":       1.12670,
  "RA": 41.309,
  "dec": -11.847
 },
 {
  "seqid": "1",
  "seqnum": 42,
  "seqtot": 122,
  "expType": "object",
  "propid": "2023B-184194",
  "object": "IBIS_wide_M490_406917",
  "expTime":      800,
  "efftime":       298.580,
  "filter": "M490",
  "approx_datetime": "2025/12/16 03:19:59.25",
  "approx_airmass":       1.11679,
  "RA": 41.625,
  "dec": -13.862
 },
 {
  "seqid": "1",
  "seqnum": 43,
  "seqtot": 122,
  "expType": "object",
  "propid": "2023B-184194",
  "object": "IBIS_wide_M490_406918",
  "expTime":      800,
  "efftime":       300.140,
  "filter": "M490",
  "approx_datetime": "2025/12/16 03:23:24.87",
  "approx_airmass":       1.12192,
  "RA": 42.352,
  "dec": -13.226
 },
 {
  "seqid": "1",
  "seqnum": 44,
  "seqtot": 122,
  "expType": "object",
  "propid": "2023B-184194",
  "object": "IBIS_wide_M490_406921",
  "expTime":      800,
  "efftime":       304.340,
  "filter": "M490",
  "approx_datetime": "2025/12/16 03:26:51.38",
  "approx_airmass":       1.12714,
  "RA": 43.055,
  "dec": -12.634
 },
 {
  "seqid": "1",
  "seqnum": 45,
  "seqtot": 122,
  "expType": "object",
  "propid": "2023B-184194",
  "object": "IBIS_wide_M490_409907",
  "expTime":      800,
  "efftime":       305.810,
  "filter": "M490",
  "approx_datetime": "2025/12/16 03:30:20.29",
  "approx_airmass":       1.13335,
  "RA": 43.349,
  "dec": -12.363
 },
 {
  "seqid": "1",
  "seqnum": 46,
  "seqtot": 122,
  "expType": "object",
  "propid": "2023B-184194",
  "object": "IBIS_wide_M490_406922",
  "expTime":      800,
  "efftime":       311.250,
  "filter": "M490",
  "approx_datetime": "2025/12/16 03:33:50.03",
  "approx_airmass":       1.13846,
  "RA": 43.791,
  "dec": -12.117
 },
 {
  "seqid": "1",
  "seqnum": 47,
  "seqtot": 122,
  "expType": "object",
  "propid": "2023B-184194",
  "object": "IBIS_wide_M490_406875",
  "expTime":      800,
  "efftime":       373.570,
  "filter": "M490",
  "approx_datetime": "2025/12/16 03:37:22.89",
  "approx_airmass":       1.13490,
  "RA": 45.267,
  "dec": -11.992
 },
 {
  "seqid": "1",
  "seqnum": 48,
  "seqtot": 122,
  "expType": "object",
  "propid": "2023B-184194",
  "object": "IBIS_wide_M490_406861",
  "expTime":      800,
  "efftime":       326.250,
  "filter": "M490",
  "approx_datetime": "2025/12/16 03:41:31.36",
  "approx_airmass":       1.13621,
  "RA": 44.142,
  "dec": -14.224
 },
 {
  "seqid": "1",
  "seqnum": 49,
  "seqtot": 122,
  "expType": "object",
  "propid": "2023B-184194",
  "object": "IBIS_wide_M490_406877",
  "expTime":      800,
  "efftime":       391.390,
  "filter": "M490",
  "approx_datetime": "2025/12/16 03:45:12.79",
  "approx_airmass":       1.14033,
  "RA": 47.230,
  "dec": -11.269
 },
 {
  "seqid": "1",
  "seqnum": 50,
  "seqtot": 122,
  "expType": "object",
  "propid": "2023B-184194",
  "object": "IBIS_wide_M490_409838",
  "expTime":      800,
  "efftime":       345.140,
  "filter": "M490",
  "approx_datetime": "2025/12/16 03:49:31.44",
  "approx_airmass":       1.14426,
  "RA": 44.840,
  "dec": -14.659
 },
 {
  "seqid": "1",
  "seqnum": 51,
  "seqtot": 122,
  "expType": "object",
  "propid": "2023B-184194",
  "object": "IBIS_wide_M490_409851",
  "expTime":      800,
  "efftime":       354.760,
  "filter": "M490",
  "approx_datetime": "2025/12/16 03:53:23.66",
  "approx_airmass":       1.13577,
  "RA": 47.783,
  "dec": -13.500
 },
 {
  "seqid": "1",
  "seqnum": 52,
  "seqtot": 122,
  "expType": "object",
  "propid": "2023B-184194",
  "object": "IBIS_wide_M490_406843",
  "expTime":      800,
  "efftime":       348.030,
  "filter": "M490",
  "approx_datetime": "2025/12/16 03:57:21.38",
  "approx_airmass":       1.13618,
  "RA": 47.918,
  "dec": -14.467
 },
 {
  "seqid": "1",
  "seqnum": 53,
  "seqtot": 122,
  "expType": "object",
  "propid": "2023B-184194",
  "object": "IBIS_wide_M490_407155",
  "expTime":      800,
  "efftime":       412.780,
  "filter": "M490",
  "approx_datetime": "2025/12/16 04:01:15.26",
  "approx_airmass":       1.13900,
  "RA": 50.693,
  "dec": -12.015
 },
 {
  "seqid": "1",
  "seqnum": 54,
  "seqtot": 122,
  "expType": "object",
  "propid": "2023B-184194",
  "object": "IBIS_wide_M490_406846",
  "expTime":      800,
  "efftime":       400.940,
  "filter": "M490",
  "approx_datetime": "2025/12/16 04:05:46.13",
  "approx_airmass":       1.13829,
  "RA": 50.789,
  "dec": -13.247
 },
 {
  "seqid": "1",
  "seqnum": 55,
  "seqtot": 122,
  "expType": "object",
  "propid": "2023B-184194",
  "object": "IBIS_wide_M490_406840",
  "expTime":      800,
  "efftime":       407.230,
  "filter": "M490",
  "approx_datetime": "2025/12/16 04:10:10.24",
  "approx_airmass":       1.13964,
  "RA": 51.378,
  "dec": -13.652
 },
 {
  "seqid": "1",
  "seqnum": 56,
  "seqtot": 122,
  "expType": "object",
  "propid": "2023B-184194",
  "object": "IBIS_wide_M490_406838",
  "expTime":      800,
  "efftime":       405.220,
  "filter": "M490",
  "approx_datetime": "2025/12/16 04:14:37.94",
  "approx_airmass":       1.13697,
  "RA": 52.094,
  "dec": -14.540
 },
 {
  "seqid": "1",
  "seqnum": 57,
  "seqtot": 122,
  "expType": "object",
  "propid": "2023B-184194",
  "object": "IBIS_wide_M490_410132",
  "expTime":      800,
  "efftime":       361.350,
  "filter": "M490",
  "approx_datetime": "2025/12/16 04:19:04.50",
  "approx_airmass":       1.14086,
  "RA": 54.054,
  "dec": -12.963
 },
 {
  "seqid": "1",
  "seqnum": 58,
  "seqtot": 122,
  "expType": "object",
  "propid": "2023B-184194",
  "object": "IBIS_wide_M490_407149",
  "expTime":      800,
  "efftime":       358.990,
  "filter": "M490",
  "approx_datetime": "2025/12/16 04:23:05.98",
  "approx_airmass":       1.15736,
  "RA": 53.149,
  "dec": -12.929
 },
 {
  "seqid": "1",
  "seqnum": 59,
  "seqtot": 122,
  "expType": "object",
  "propid": "2023B-184194",
  "object": "IBIS_wide_M490_410138",
  "expTime":      800,
  "efftime":       402.640,
  "filter": "M490",
  "approx_datetime": "2025/12/16 04:27:06.12",
  "approx_airmass":       1.16725,
  "RA": 54.614,
  "dec": -11.129
 },
 {
  "seqid": "1",
  "seqnum": 60,
  "seqtot": 122,
  "expType": "object",
  "propid": "2023B-184194",
  "object": "IBIS_wide_M490_410137",
  "expTime":      800,
  "efftime":       387.520,
  "filter": "M490",
  "approx_datetime": "2025/12/16 04:31:31.20",
  "approx_airmass":       1.17900,
  "RA": 53.924,
  "dec": -11.746
 },
 {
  "seqid": "1",
  "seqnum": 61,
  "seqtot": 122,
  "expType": "object",
  "propid": "2023B-184194",
  "object": "IBIS_wide_M490_407152",
  "expTime":      800,
  "efftime":       386.790,
  "filter": "M490",
  "approx_datetime": "2025/12/16 04:35:47.64",
  "approx_airmass":       1.19145,
  "RA": 54.100,
  "dec": -11.324
 },
 {
  "seqid": "1",
  "seqnum": 62,
  "seqtot": 122,
  "expType": "object",
  "propid": "2023B-184194",
  "object": "IBIS_wide_M490_407151",
  "expTime":      800,
  "efftime":       373.300,
  "filter": "M490",
  "approx_datetime": "2025/12/16 04:40:03.66",
  "approx_airmass":       1.20320,
  "RA": 53.480,
  "dec": -12.042
 },
 {
  "seqid": "1",
  "seqnum": 63,
  "seqtot": 122,
  "expType": "object",
  "propid": "2023B-184194",
  "object": "IBIS_wide_M490_407148",
  "expTime":      800,
  "efftime":       370.150,
  "filter": "M490",
  "approx_datetime": "2025/12/16 04:44:11.98",
  "approx_airmass":       1.22033,
  "RA": 52.751,
  "dec": -12.387
 },
 {
  "seqid": "1",
  "seqnum": 64,
  "seqtot": 122,
  "expType": "object",
  "propid": "2023B-184194",
  "object": "IBIS_wide_M490_407169",
  "expTime":      800,
  "efftime":       370.220,
  "filter": "M490",
  "approx_datetime": "2025/12/16 04:48:18.49",
  "approx_airmass":       1.23412,
  "RA": 54.317,
  "dec": -10.192
 },
 {
  "seqid": "1",
  "seqnum": 65,
  "seqtot": 122,
  "expType": "object",
  "propid": "2023B-184194",
  "object": "IBIS_wide_M490_410144",
  "expTime":      800,
  "efftime":       356.570,
  "filter": "M490",
  "approx_datetime": "2025/12/16 04:52:25.05",
  "approx_airmass":       1.24807,
  "RA": 53.888,
  "dec": -10.613
 },
 {
  "seqid": "1",
  "seqnum": 66,
  "seqtot": 122,
  "expType": "object",
  "propid": "2023B-184194",
  "object": "IBIS_wide_M490_407154",
  "expTime":      800,
  "efftime":       393.950,
  "filter": "M490",
  "approx_datetime": "2025/12/16 04:56:23.80",
  "approx_airmass":       1.26392,
  "RA": 52.134,
  "dec": -12.782
 },
 {
  "seqid": "1",
  "seqnum": 67,
  "seqtot": 122,
  "expType": "object",
  "propid": "2023B-184194",
  "object": "IBIS_wide_M490_407158",
  "expTime":      800,
  "efftime":       350.060,
  "filter": "M490",
  "approx_datetime": "2025/12/16 05:00:43.91",
  "approx_airmass":       1.27920,
  "RA": 53.589,
  "dec": -10.709
 },
 {
  "seqid": "1",
  "seqnum": 68,
  "seqtot": 122,
  "expType": "object",
  "propid": "2023B-184194",
  "object": "IBIS_wide_M490_410143",
  "expTime":      800,
  "efftime":       356.290,
  "filter": "M490",
  "approx_datetime": "2025/12/16 05:04:38.95",
  "approx_airmass":       1.29452,
  "RA": 53.213,
  "dec": -11.142
 },
 {
  "seqid": "1",
  "seqnum": 69,
  "seqtot": 122,
  "expType": "object",
  "propid": "2023B-184194",
  "object": "IBIS_wide_M490_407157",
  "expTime":      800,
  "efftime":       363.010,
  "filter": "M490",
  "approx_datetime": "2025/12/16 05:08:37.54",
  "approx_airmass":       1.31219,
  "RA": 52.862,
  "dec": -11.437
 },
 {
  "seqid": "1",
  "seqnum": 70,
  "seqtot": 122,
  "expType": "object",
  "propid": "2023B-184194",
  "object": "IBIS_wide_M490_406839",
  "expTime":      800,
  "efftime":       359.460,
  "filter": "M490",
  "approx_datetime": "2025/12/16 05:12:39.98",
  "approx_airmass":       1.33164,
  "RA": 50.865,
  "dec": -14.344
 },
 {
  "seqid": "1",
  "seqnum": 71,
  "seqtot": 122,
  "expType": "object",
  "propid": "2023B-184194",
  "object": "IBIS_wide_M490_410140",
  "expTime":      800,
  "efftime":       366.910,
  "filter": "M490",
  "approx_datetime": "2025/12/16 05:16:40.38",
  "approx_airmass":       1.34969,
  "RA": 52.472,
  "dec": -11.692
 },
 {
  "seqid": "1",
  "seqnum": 72,
  "seqtot": 122,
  "expType": "object",
  "propid": "2023B-184194",
  "object": "IBIS_wide_M490_410157",
  "expTime":      800,
  "efftime":       333.000,
  "filter": "M490",
  "approx_datetime": "2025/12/16 05:20:45.05",
  "approx_airmass":       1.37053,
  "RA": 53.753,
  "dec": -9.577
 },
 {
  "seqid": "1",
  "seqnum": 73,
  "seqtot": 122,
  "expType": "object",
  "propid": "2023B-184194",
  "object": "IBIS_wide_M490_422229",
  "expTime":      800,
  "efftime":       298.610,
  "filter": "M490",
  "approx_datetime": "2025/12/16 05:24:30.33",
  "approx_airmass":       1.35572,
  "RA": 130.212,
  "dec": -3.277
 },
 {
  "seqid": "1",
  "seqnum": 74,
  "seqtot": 122,
  "expType": "object",
  "propid": "2023B-184194",
  "object": "IBIS_wide_M490_419252",
  "expTime":      800,
  "efftime":       306.500,
  "filter": "M490",
  "approx_datetime": "2025/12/16 05:27:55.97",
  "approx_airmass":       1.34631,
  "RA": 128.980,
  "dec": -1.772
 },
 {
  "seqid": "1",
  "seqnum": 75,
  "seqtot": 122,
  "expType": "object",
  "propid": "2023B-184194",
  "object": "IBIS_wide_M490_422203",
  "expTime":      800,
  "efftime":       288.140,
  "filter": "M490",
  "approx_datetime": "2025/12/16 05:31:26.11",
  "approx_airmass":       1.33305,
  "RA": 132.127,
  "dec": -5.071
 },
 {
  "seqid": "1",
  "seqnum": 76,
  "seqtot": 122,
  "expType": "object",
  "propid": "2023B-184194",
  "object": "IBIS_wide_M490_422205",
  "expTime":      800,
  "efftime":       288.190,
  "filter": "M490",
  "approx_datetime": "2025/12/16 05:34:45.76",
  "approx_airmass":       1.32146,
  "RA": 131.544,
  "dec": -4.369
 },
 {
  "seqid": "1",
  "seqnum": 77,
  "seqtot": 122,
  "expType": "object",
  "propid": "2023B-184194",
  "object": "IBIS_wide_M490_422197",
  "expTime":      800,
  "efftime":       290.050,
  "filter": "M490",
  "approx_datetime": "2025/12/16 05:38:05.44",
  "approx_airmass":       1.30996,
  "RA": 132.809,
  "dec": -5.710
 },
 {
  "seqid": "1",
  "seqnum": 78,
  "seqtot": 122,
  "expType": "object",
  "propid": "2023B-184194",
  "object": "IBIS_wide_M490_419244",
  "expTime":      800,
  "efftime":       298.500,
  "filter": "M490",
  "approx_datetime": "2025/12/16 05:41:26.18",
  "approx_airmass":       1.30239,
  "RA": 130.456,
  "dec": -2.976
 },
 {
  "seqid": "1",
  "seqnum": 79,
  "seqtot": 122,
  "expType": "object",
  "propid": "2023B-184194",
  "object": "IBIS_wide_M490_419250",
  "expTime":      800,
  "efftime":       303.140,
  "filter": "M490",
  "approx_datetime": "2025/12/16 05:44:51.75",
  "approx_airmass":       1.29246,
  "RA": 129.852,
  "dec": -2.345
 },
 {
  "seqid": "1",
  "seqnum": 80,
  "seqtot": 122,
  "expType": "object",
  "propid": "2023B-184194",
  "object": "IBIS_wide_M490_419242",
  "expTime":      800,
  "efftime":       287.130,
  "filter": "M490",
  "approx_datetime": "2025/12/16 05:48:19.98",
  "approx_airmass":       1.28390,
  "RA": 131.374,
  "dec": -3.585
 },
 {
  "seqid": "1",
  "seqnum": 81,
  "seqtot": 122,
  "expType": "object",
  "propid": "2023B-184194",
  "object": "IBIS_wide_M490_419218",
  "expTime":      800,
  "efftime":       285.430,
  "filter": "M490",
  "approx_datetime": "2025/12/16 05:51:39.05",
  "approx_airmass":       1.27364,
  "RA": 132.609,
  "dec": -4.781
 },
 {
  "seqid": "1",
  "seqnum": 82,
  "seqtot": 122,
  "expType": "object",
  "propid": "2023B-184194",
  "object": "IBIS_wide_M490_419210",
  "expTime":      800,
  "efftime":       297.000,
  "filter": "M490",
  "approx_datetime": "2025/12/16 05:54:57.15",
  "approx_airmass":       1.26624,
  "RA": 134.007,
  "dec": -5.973
 },
 {
  "seqid": "1",
  "seqnum": 83,
  "seqtot": 122,
  "expType": "object",
  "propid": "2023B-184194",
  "object": "IBIS_wide_M490_419212",
  "expTime":      800,
  "efftime":       288.930,
  "filter": "M490",
  "approx_datetime": "2025/12/16 05:58:21.87",
  "approx_airmass":       1.25754,
  "RA": 133.574,
  "dec": -5.395
 },
 {
  "seqid": "1",
  "seqnum": 84,
  "seqtot": 122,
  "expType": "object",
  "propid": "2023B-184194",
  "object": "IBIS_wide_M490_422206",
  "expTime":      800,
  "efftime":       287.500,
  "filter": "M490",
  "approx_datetime": "2025/12/16 06:01:41.97",
  "approx_airmass":       1.25099,
  "RA": 132.276,
  "dec": -3.934
 },
 {
  "seqid": "1",
  "seqnum": 85,
  "seqtot": 122,
  "expType": "object",
  "propid": "2023B-184194",
  "object": "IBIS_wide_M490_422108",
  "expTime":      800,
  "efftime":       323.610,
  "filter": "M490",
  "approx_datetime": "2025/12/16 06:05:01.26",
  "approx_airmass":       1.24791,
  "RA": 135.733,
  "dec": -6.731
 },
 {
  "seqid": "1",
  "seqnum": 86,
  "seqtot": 122,
  "expType": "object",
  "propid": "2023B-184194",
  "object": "IBIS_wide_M490_419223",
  "expTime":      800,
  "efftime":       285.950,
  "filter": "M490",
  "approx_datetime": "2025/12/16 06:08:41.18",
  "approx_airmass":       1.24060,
  "RA": 132.571,
  "dec": -3.529
 },
 {
  "seqid": "1",
  "seqnum": 87,
  "seqtot": 122,
  "expType": "object",
  "propid": "2023B-184194",
  "object": "IBIS_wide_M490_419127",
  "expTime":      800,
  "efftime":       304.040,
  "filter": "M490",
  "approx_datetime": "2025/12/16 06:11:59.58",
  "approx_airmass":       1.23304,
  "RA": 135.360,
  "dec": -5.933
 },
 {
  "seqid": "1",
  "seqnum": 88,
  "seqtot": 122,
  "expType": "object",
  "propid": "2023B-184194",
  "object": "IBIS_wide_M490_419125",
  "expTime":      800,
  "efftime":       322.070,
  "filter": "M490",
  "approx_datetime": "2025/12/16 06:15:28.31",
  "approx_airmass":       1.22559,
  "RA": 136.125,
  "dec": -6.507
 },
 {
  "seqid": "1",
  "seqnum": 89,
  "seqtot": 122,
  "expType": "object",
  "propid": "2023B-184194",
  "object": "IBIS_wide_M490_422111",
  "expTime":      800,
  "efftime":       315.100,
  "filter": "M490",
  "approx_datetime": "2025/12/16 06:19:07.35",
  "approx_airmass":       1.22087,
  "RA": 136.373,
  "dec": -6.302
 },
 {
  "seqid": "1",
  "seqnum": 90,
  "seqtot": 122,
  "expType": "object",
  "propid": "2023B-184194",
  "object": "IBIS_wide_M490_422113",
  "expTime":      800,
  "efftime":       294.460,
  "filter": "M490",
  "approx_datetime": "2025/12/16 06:22:42.41",
  "approx_airmass":       1.21255,
  "RA": 135.689,
  "dec": -5.624
 },
 {
  "seqid": "1",
  "seqnum": 91,
  "seqtot": 122,
  "expType": "object",
  "propid": "2023B-184194",
  "object": "IBIS_wide_M490_422105",
  "expTime":      800,
  "efftime":       329.890,
  "filter": "M490",
  "approx_datetime": "2025/12/16 06:26:05.67",
  "approx_airmass":       1.20541,
  "RA": 137.047,
  "dec": -6.757
 },
 {
  "seqid": "1",
  "seqnum": 92,
  "seqtot": 122,
  "expType": "object",
  "propid": "2023B-184194",
  "object": "IBIS_wide_M490_419126",
  "expTime":      800,
  "efftime":       302.820,
  "filter": "M490",
  "approx_datetime": "2025/12/16 06:29:49.18",
  "approx_airmass":       1.20198,
  "RA": 136.825,
  "dec": -6.045
 },
 {
  "seqid": "1",
  "seqnum": 93,
  "seqtot": 122,
  "expType": "object",
  "propid": "2023B-184194",
  "object": "IBIS_wide_M490_419120",
  "expTime":      800,
  "efftime":       328.640,
  "filter": "M490",
  "approx_datetime": "2025/12/16 06:33:17.22",
  "approx_airmass":       1.19448,
  "RA": 137.557,
  "dec": -6.650
 },
 {
  "seqid": "1",
  "seqnum": 94,
  "seqtot": 122,
  "expType": "object",
  "propid": "2023B-184194",
  "object": "IBIS_wide_M490_419128",
  "expTime":      800,
  "efftime":       291.430,
  "filter": "M490",
  "approx_datetime": "2025/12/16 06:37:00.02",
  "approx_airmass":       1.18875,
  "RA": 136.236,
  "dec": -5.334
 },
 {
  "seqid": "1",
  "seqnum": 95,
  "seqtot": 122,
  "expType": "object",
  "propid": "2023B-184194",
  "object": "IBIS_wide_M490_422104",
  "expTime":      800,
  "efftime":       327.110,
  "filter": "M490",
  "approx_datetime": "2025/12/16 06:40:21.55",
  "approx_airmass":       1.18623,
  "RA": 138.611,
  "dec": -6.840
 },
 {
  "seqid": "1",
  "seqnum": 96,
  "seqtot": 122,
  "expType": "object",
  "propid": "2023B-184194",
  "object": "IBIS_wide_M490_419283",
  "expTime":      800,
  "efftime":       299.620,
  "filter": "M490",
  "approx_datetime": "2025/12/16 06:44:03.47",
  "approx_airmass":       1.18442,
  "RA": 137.668,
  "dec": -5.487
 },
 {
  "seqid": "1",
  "seqnum": 97,
  "seqtot": 122,
  "expType": "object",
  "propid": "2023B-184194",
  "object": "IBIS_wide_M490_422263",
  "expTime":      800,
  "efftime":       314.070,
  "filter": "M490",
  "approx_datetime": "2025/12/16 06:47:29.68",
  "approx_airmass":       1.18196,
  "RA": 138.578,
  "dec": -5.764
 },
 {
  "seqid": "1",
  "seqnum": 98,
  "seqtot": 122,
  "expType": "object",
  "propid": "2023B-184194",
  "object": "IBIS_wide_M490_422252",
  "expTime":      800,
  "efftime":       317.790,
  "filter": "M490",
  "approx_datetime": "2025/12/16 06:51:04.15",
  "approx_airmass":       1.17603,
  "RA": 140.129,
  "dec": -6.885
 },
 {
  "seqid": "1",
  "seqnum": 99,
  "seqtot": 122,
  "expType": "object",
  "propid": "2023B-184194",
  "object": "IBIS_wide_M490_422261",
  "expTime":      800,
  "efftime":       316.490,
  "filter": "M490",
  "approx_datetime": "2025/12/16 06:54:40.74",
  "approx_airmass":       1.16957,
  "RA": 139.443,
  "dec": -6.278
 },
 {
  "seqid": "1",
  "seqnum": 100,
  "seqtot": 122,
  "expType": "object",
  "propid": "2023B-184194",
  "object": "IBIS_wide_M490_419267",
  "expTime":      800,
  "efftime":       312.660,
  "filter": "M490",
  "approx_datetime": "2025/12/16 06:58:16.59",
  "approx_airmass":       1.16714,
  "RA": 140.410,
  "dec": -6.577
 },
 {
  "seqid": "1",
  "seqnum": 101,
  "seqtot": 122,
  "expType": "object",
  "propid": "2023B-184194",
  "object": "IBIS_wide_M490_422253",
  "expTime":      800,
  "efftime":       310.230,
  "filter": "M490",
  "approx_datetime": "2025/12/16 07:01:50.26",
  "approx_airmass":       1.16621,
  "RA": 140.809,
  "dec": -6.297
 },
 {
  "seqid": "1",
  "seqnum": 102,
  "seqtot": 122,
  "expType": "object",
  "propid": "2023B-184194",
  "object": "IBIS_wide_M490_419268",
  "expTime":      800,
  "efftime":       316.870,
  "filter": "M490",
  "approx_datetime": "2025/12/16 07:05:22.53",
  "approx_airmass":       1.16232,
  "RA": 141.558,
  "dec": -6.596
 },
 {
  "seqid": "1",
  "seqnum": 103,
  "seqtot": 122,
  "expType": "object",
  "propid": "2023B-184194",
  "object": "IBIS_wide_M490_422248",
  "expTime":      800,
  "efftime":       320.420,
  "filter": "M490",
  "approx_datetime": "2025/12/16 07:08:58.60",
  "approx_airmass":       1.16182,
  "RA": 142.782,
  "dec": -6.893
 },
 {
  "seqid": "1",
  "seqnum": 104,
  "seqtot": 122,
  "expType": "object",
  "propid": "2023B-184194",
  "object": "IBIS_wide_M490_422256",
  "expTime":      800,
  "efftime":       315.070,
  "filter": "M490",
  "approx_datetime": "2025/12/16 07:12:36.70",
  "approx_airmass":       1.15639,
  "RA": 141.418,
  "dec": -5.823
 },
 {
  "seqid": "1",
  "seqnum": 105,
  "seqtot": 122,
  "expType": "object",
  "propid": "2023B-184194",
  "object": "IBIS_wide_M490_419269",
  "expTime":      800,
  "efftime":       323.410,
  "filter": "M490",
  "approx_datetime": "2025/12/16 07:16:11.74",
  "approx_airmass":       1.15552,
  "RA": 142.455,
  "dec": -6.006
 },
 {
  "seqid": "1",
  "seqnum": 106,
  "seqtot": 122,
  "expType": "object",
  "propid": "2023B-184194",
  "object": "IBIS_wide_M490_418972",
  "expTime":      800,
  "efftime":       308.070,
  "filter": "M490",
  "approx_datetime": "2025/12/16 07:19:51.54",
  "approx_airmass":       1.15410,
  "RA": 143.976,
  "dec": -6.573
 },
 {
  "seqid": "1",
  "seqnum": 107,
  "seqtot": 122,
  "expType": "object",
  "propid": "2023B-184194",
  "object": "IBIS_wide_M490_419272",
  "expTime":      800,
  "efftime":       322.810,
  "filter": "M490",
  "approx_datetime": "2025/12/16 07:23:22.58",
  "approx_airmass":       1.15270,
  "RA": 142.991,
  "dec": -5.475
 },
 {
  "seqid": "1",
  "seqnum": 108,
  "seqtot": 122,
  "expType": "object",
  "propid": "2023B-184194",
  "object": "IBIS_wide_M490_427951",
  "expTime":      800,
  "efftime":       308.360,
  "filter": "M490",
  "approx_datetime": "2025/12/16 07:27:02.05",
  "approx_airmass":       1.14976,
  "RA": 144.002,
  "dec": -5.838
 },
 {
  "seqid": "1",
  "seqnum": 109,
  "seqtot": 122,
  "expType": "object",
  "propid": "2023B-184194",
  "object": "IBIS_wide_M490_424963",
  "expTime":      800,
  "efftime":       307.520,
  "filter": "M490",
  "approx_datetime": "2025/12/16 07:30:33.25",
  "approx_airmass":       1.14466,
  "RA": 145.450,
  "dec": -6.750
 },
 {
  "seqid": "1",
  "seqnum": 110,
  "seqtot": 122,
  "expType": "object",
  "propid": "2023B-184194",
  "object": "IBIS_wide_M490_424965",
  "expTime":      800,
  "efftime":       305.330,
  "filter": "M490",
  "approx_datetime": "2025/12/16 07:34:03.98",
  "approx_airmass":       1.14164,
  "RA": 144.582,
  "dec": -5.964
 },
 {
  "seqid": "1",
  "seqnum": 111,
  "seqtot": 122,
  "expType": "object",
  "propid": "2023B-184194",
  "object": "IBIS_wide_M490_427948",
  "expTime":      800,
  "efftime":       305.750,
  "filter": "M490",
  "approx_datetime": "2025/12/16 07:37:33.45",
  "approx_airmass":       1.14008,
  "RA": 145.347,
  "dec": -6.065
 },
 {
  "seqid": "1",
  "seqnum": 112,
  "seqtot": 122,
  "expType": "object",
  "propid": "2023B-184194",
  "object": "IBIS_wide_M490_427949",
  "expTime":      800,
  "efftime":       310.330,
  "filter": "M490",
  "approx_datetime": "2025/12/16 07:41:03.17",
  "approx_airmass":       1.13592,
  "RA": 145.884,
  "dec": -6.313
 },
 {
  "seqid": "1",
  "seqnum": 113,
  "seqtot": 122,
  "expType": "object",
  "propid": "2023B-184194",
  "object": "IBIS_wide_M490_424967",
  "expTime":      800,
  "efftime":       367.490,
  "filter": "M490",
  "approx_datetime": "2025/12/16 07:44:35.50",
  "approx_airmass":       1.13268,
  "RA": 146.798,
  "dec": -6.685
 },
 {
  "seqid": "1",
  "seqnum": 114,
  "seqtot": 122,
  "expType": "object",
  "propid": "2023B-184194",
  "object": "IBIS_wide_M490_427937",
  "expTime":      800,
  "efftime":       412.330,
  "filter": "M490",
  "approx_datetime": "2025/12/16 07:48:40.49",
  "approx_airmass":       1.13121,
  "RA": 147.863,
  "dec": -6.873
 },
 {
  "seqid": "1",
  "seqnum": 115,
  "seqtot": 122,
  "expType": "object",
  "propid": "2023B-184194",
  "object": "IBIS_wide_M490_427955",
  "expTime":      800,
  "efftime":       377.420,
  "filter": "M490",
  "approx_datetime": "2025/12/16 07:53:11.11",
  "approx_airmass":       1.12953,
  "RA": 146.461,
  "dec": -5.675
 },
 {
  "seqid": "1",
  "seqnum": 116,
  "seqtot": 122,
  "expType": "object",
  "propid": "2023B-184194",
  "object": "IBIS_wide_M490_424952",
  "expTime":      800,
  "efftime":       385.200,
  "filter": "M490",
  "approx_datetime": "2025/12/16 07:57:21.78",
  "approx_airmass":       1.12463,
  "RA": 148.226,
  "dec": -6.581
 },
 {
  "seqid": "1",
  "seqnum": 117,
  "seqtot": 122,
  "expType": "object",
  "propid": "2023B-184194",
  "object": "IBIS_wide_M490_427936",
  "expTime":      800,
  "efftime":       355.210,
  "filter": "M490",
  "approx_datetime": "2025/12/16 08:01:36.89",
  "approx_airmass":       1.12094,
  "RA": 149.244,
  "dec": -6.975
 },
 {
  "seqid": "1",
  "seqnum": 118,
  "seqtot": 122,
  "expType": "object",
  "propid": "2023B-184194",
  "object": "IBIS_wide_M490_427938",
  "expTime":      800,
  "efftime":       349.840,
  "filter": "M490",
  "approx_datetime": "2025/12/16 08:05:34.87",
  "approx_airmass":       1.11980,
  "RA": 148.601,
  "dec": -6.281
 },
 {
  "seqid": "1",
  "seqnum": 119,
  "seqtot": 122,
  "expType": "object",
  "propid": "2023B-184194",
  "object": "IBIS_wide_M490_424953",
  "expTime":      800,
  "efftime":       329.750,
  "filter": "M490",
  "approx_datetime": "2025/12/16 08:09:29.78",
  "approx_airmass":       1.11611,
  "RA": 149.605,
  "dec": -6.710
 },
 {
  "seqid": "1",
  "seqnum": 120,
  "seqtot": 122,
  "expType": "object",
  "propid": "2023B-184194",
  "object": "IBIS_wide_M490_427933",
  "expTime":      800,
  "efftime":       324.750,
  "filter": "M490",
  "approx_datetime": "2025/12/16 08:13:13.21",
  "approx_airmass":       1.11506,
  "RA": 150.673,
  "dec": -6.896
 },
 {
  "seqid": "1",
  "seqnum": 121,
  "seqtot": 122,
  "expType": "object",
  "propid": "2023B-184194",
  "object": "IBIS_wide_M490_424948",
  "expTime":      800,
  "efftime":       321.720,
  "filter": "M490",
  "approx_datetime": "2025/12/16 08:16:53.78",
  "approx_airmass":       1.11692,
  "RA": 151.041,
  "dec": -6.423
 }
]
